Workbook
Name UPDATE: 'Data Sheet'!$E$1

Sheet Data Sheet
A1: COMPANY NAME | B1: TATA STEEL LTD | E1: =IF(B2<>B3, "A NEW VERSION OF THE WORKSHEET IS AVAILABLE", "")
A2: LATEST VERSION | B2: 2.1 | E2: PLEASE DO NOT MAKE ANY CHANGES TO THIS SHEET
A3: CURRENT VERSION | B3: 2.1
A5: META
A6: Number of shares | B6: =IF(B9>0, B9/B8, 0) -> 1248.3526
A7: Face Value | B7: 1
A8: Current Price | B8: 188.4
A9: Market Capitalization | B9: 235189.63
A15: PROFIT & LOSS
A16: Report Date | B16: 42825 | C16: 43190 | D16: 43555 | E16: 43921 | F16: 44286 | G16: 44651 | H16: 45016 | I16: 45382 | J16: 45747 | K16: 46112
A17: Sales | B17: 112299.42 | C17: 123249.07 | D17: 157668.99 | E17: 139816.65 | F17: 156477.4 | G17: 243959.17 | H17: 243352.69 | I17: 229170.78 | J17: 218542.51 | K17: 232139.94
A18: Raw Material Cost | B18: 43843.03 | C18: 46137.01 | D18: 60877.05 | E18: 58039.99 | F18: 55100.81 | G18: 91076.61 | H18: 116597.19 | I18: 97506.39 | J18: 95097.3 | K18: 92628.07
A19: Change in Inventory | B19: 4538.13 | C19: -99.31 | D19: 96.71 | E19: 565.24 | F19: -1516.77 | G19: 7597.87 | H19: 3358.89 | I19: -4409.35 | J19: 96.65 | K19: -989.62
A20: Power and Fuel | B20: 5220.83 | C20: 4440.43 | D20: 5316.56 | E20: 5319.92 | F20: 5708.42 | G20: 8028.29 | H20: 9526.91 | I20: 16612.61 | J20: 13124.85 | K20: 14333.15
A21: Other Mfr. Exp | B21: 15799.14 | C21: 16955.79 | D21: 20734.28 | E21: 21232.69 | F21: 20744.93 | G21: 28834.06 | H21: 33144.83 | I21: 40116.91 | J21: 38700.5 | K21: 37485.96
A22: Employee Cost | B22: 17252.22 | C22: 17077.51 | D22: 18758.87 | E22: 18533.58 | F22: 19908.81 | G22: 23264.1 | H22: 22419.32 | I22: 24509.58 | J22: 24888.99 | K22: 25998.98
A23: Selling and admin | B23: 13772.32 | C23: 14423.87 | D23: 16917.14 | E23: 15599.07 | F23: 17509.77 | G23: 27445.67 | H23: 25519.92 | I23: 14453.57 | J23: 12137.26 | K23: 13348.99
A24: Other Expenses | B24: 7806.38 | C24: 2681.96 | D24: 5843.58 | E24: 4193.58 | F24: 5483.63 | G24: 9418.36 | H24: 7203.25 | I24: 9314.45 | J24: 9391.81 | K24: 13002.73
A25: Other Income | B25: -3789.11 | C25: 10898.41 | D25: 1524.31 | E25: -2883.63 | F25: 179.78 | G25: 1299.99 | H25: 1568.86 | I25: -6005.23 | J25: 876.7 | K25: 737.82
A26: Depreciation | B26: 5672.88 | C26: 5741.7 | D26: 7341.83 | E26: 8440.73 | F26: 9233.64 | G26: 9100.87 | H26: 9335.2 | I26: 9882.16 | J26: 10421.33 | K26: 11954.51
A27: Interest | B27: 5072.2 | C27: 5454.74 | D27: 7660.1 | E27: 7533.46 | F27: 7606.71 | G27: 5462.2 | H27: 6298.7 | I27: 7507.57 | J27: 7340.95 | K27: 7167.06
... A31: Dividend Amount | B31: 970.24 | C31: 1144.95 | D31: 1488.42 | E31: 1144.95 | F31: 2994.02 | G31: 6228.17 | H31: 4396.46 | I31: 4490.78 | J31: 4490.78 | K31: 4989.76
C33: =C30-C25 -> 2535.92
B35: =379 -> 379
A37: EBITDA | B37: =B30+B29+B27+B26 -> 9282.29 | C37: =C30+C29+C27+C26 -> 28023.1 | D37: =D30+D29+D27+D26 -> 31938.69 | E37: =E30+E29+E27+E26 -> 14962.32 | F37: =F30+F29+F27+F26 -> 29984.47 | G37: =G30+G29+G27+G26 -> 63194.55 | H37: =H30+H29+H27+H26 -> 34554.07 | I37: =I30+I29+I27+I26 -> 16714.86 | ... K37: =K30+K29+K27+K26 -> 34998.31
A40: Quarters
A41: Report Date | B41: 45382 | C41: 45473 | D41: 45565 | E41: 45657 | F41: 45747 | G41: 45838 | H41: 45930 | I41: 46022 | J41: 46112 | K41: 46203
A42: Sales | B42: 58687.31 | C42: 54771.39 | D42: 53904.71 | E42: 53648.3 | F42: 56218.11 | G42: 53178.12 | H42: 58689.29 | I42: 57002.4 | J42: 63270.13 | K42: 60794.29
A43: Expenses | B43: 52086.68 | C43: 48076.92 | D43: 47788.92 | E43: 47744.81 | F43: 49658.89 | G43: 45750.58 | H43: 49792.75 | I43: 48802.7 | J43: 53441.47 | K43: 51529.95
A44: Other Income | B44: -381.56 | C44: -5.51 | D44: 616.68 | E44: 141.82 | F44: 149.19 | G44: 236.27 | H44: -6.11 | I44: 465.17 | J44: 42.49 | K44: -16.65
A45: Depreciation | B45: 2567.95 | C45: 2535.43 | D45: 2596.74 | E45: 2569.19 | F45: 2719.97 | G45: 2744.3 | H45: 2893 | I45: 3048.81 | J45: 3268.4 | K45: 3639.65
A46: Interest | B46: 1842.25 | C46: 1776.71 | D46: 1971.4 | E46: 1804.09 | F46: 1788.75 | G46: 1852.43 | H46: 1774.96 | I46: 1747.29 | J46: 1792.38 | K46: 1770.51
A47: Profit before tax | B47: 1808.87 | C47: 2376.82 | D47: 2164.33 | E47: 1672.03 | F47: 2199.69 | G47: 3067.08 | H47: 4222.47 | I47: 3868.77 | J47: 4810.37 | K47: 3837.53
A48: Tax | B48: 1254.31 | C48: 1458.25 | D48: 1405.49 | E48: 1376.54 | F48: 998.81 | G48: 1059.72 | H48: 1039.38 | I48: 1138.4 | J48: 1845.37 | K48: 1452.29
A49: Net profit | B49: 611.48 | C49: 959.61 | D49: 833.45 | E49: 326.64 | F49: 1300.81 | G49: 2077.68 | H49: 3101.75 | I49: 2688.7 | J49: 2925.74 | K49: 2318.35
A50: Operating Profit | B50: 6600.63 | C50: 6694.47 | D50: 6115.79 | E50: 5903.49 | F50: 6559.22 | G50: 7427.54 | H50: 8896.54 | I50: 8199.7 | J50: 9828.66 | K50: 9264.34
A55: BALANCE SHEET
A56: Report Date | B56: 42825 | C56: 43190 | D56: 43555 | E56: 43921 | F56: 44286 | G56: 44651 | H56: 45016 | I56: 45382 | J56: 45747 | K56: 46112
A57: Equity Share Capital | B57: 970.24 | C57: 1144.95 | D57: 1144.94 | E57: 1144.95 | F57: 1197.61 | G57: 1221.21 | H57: 1221.24 | I57: 1247.44 | J57: 1247.44 | K57: 1247.44
A58: Reserves | B58: 36849.08 | C58: 59725.67 | D58: 67780.14 | E58: 72431.35 | F58: 73041.16 | G58: 113221.83 | H58: 101860.86 | I58: 90788.32 | J58: 89922.19 | K58: 100920.21
A59: Borrowings | B59: 83014.49 | C59: 92147.05 | D59: 100816.22 | E59: 116328.2 | F59: 88501.41 | G59: 75561.35 | H59: 84893.05 | I59: 87082.12 | J59: 94801.05 | K59: 92381.68
A60: Other Liabilities | B60: 51613.56 | C60: 55704.47 | D60: 63032.14 | E60: 59244.62 | F60: 81169.01 | G60: 92417.28 | H60: 97420.63 | I60: 90194.54 | J60: 89487.9 | K60: 101965.29
A61: Total | B61: 172447.37 | C61: 208722.14 | D61: 232773.44 | E61: 249149.12 | F61: 243909.19 | G61: 282421.67 | H61: 285395.78 | I61: 269312.42 | J61: 275458.58 | K61: 296514.62
A62: Net Block | B62: 92006.55 | C62: 96104.89 | D62: 124441.91 | E62: 134550.66 | F62: 135775.18 | G62: 133287.83 | H62: 146621.46 | I62: 148814.38 | J62: 150914.06 | K62: 179908.13
A63: Capital Work in Progress | B63: 15784.13 | C63: 16614.41 | D63: 18641.21 | E63: 19496.83 | F63: 19007.4 | G63: 22045.55 | H63: 31213.02 | I63: 34355.53 | J63: 41622.35 | K63: 28496.71
A64: Investments | B64: 12457.12 | C64: 17899.47 | D64: 5738.17 | E64: 6285.18 | F64: 10681.93 | G64: 13139.85 | H64: 8410.31 | I64: 6257.57 | J64: 6194.11 | K64: 7088.85
A65: Other Assets | B65: 52199.57 | C65: 78103.37 | D65: 83952.15 | E65: 88816.45 | F65: 78444.68 | G65: 113948.44 | H65: 99150.99 | I65: 79884.94 | J65: 76728.06 | K65: 81020.93
A66: Total | B66: 172447.37 | C66: 208722.14 | D66: 232773.44 | E66: 249149.12 | F66: 243909.19 | G66: 282421.67 | H66: 285395.78 | I66: 269312.42 | J66: 275458.58 | K66: 296514.62
A67: Receivables | B67: 11586.82 | C67: 12415.52 | D67: 11811 | E67: 7884.91 | F67: 9539.84 | G67: 12246.43 | H67: 8257.24 | I67: 6263.53 | J67: 5260.06 | K67: 4916.89
... A70: No. of Equity Shares | B70: 970436562 | C70: 1203340563 | D70: 1203331928 | E70: 1203332459 | F70: 1203334622 | G70: 1221566453 | H70: 12212353070 | I70: 12474347611 | J70: 12477659071 | K70: 12477659071
A71: New Bonus Shares
A72: Face value | B72: 10 | C72: 10 | D72: 10 | E72: 10 | F72: 10 | G72: 10 | H72: 1 | I72: 1 | J72: 1 | K72: 1
A75: Other Assets | B75: =B65-SUM(B67:B69) -> 10887.88 | C75: =C65-SUM(C67:C69) -> 29418.96 | D75: =D65-SUM(D67:D69) -> 37143.68 | E75: =E65-SUM(E67:E69) -> 41808.1 | F75: =F65-SUM(F67:F69) -> 29846.28 | G75: =G65-SUM(G67:G69) -> 36978.69 | H75: =H65-SUM(H67:H69) -> 23121.16 | I75: =I65-SUM(I67:I69) -> 15786.18 | ... K75: =K65-SUM(K67:K69) -> 18797.29
A80: CASH FLOW:
A81: Report Date | B81: 42825 | C81: 43190 | D81: 43555 | E81: 43921 | F81: 44286 | G81: 44651 | H81: 45016 | I81: 45382 | J81: 45747 | K81: 46112
A82: Cash from Operating Activity | B82: 10824.36 | C82: 8023.39 | D82: 25335.95 | E82: 20168.72 | F82: 44326.68 | G82: 44380.99 | H82: 21683.08 | I82: 20300.67 | J82: 23137.58 | K82: 35064.46
A83: Cash from Investing Activity | B83: -9489.65 | C83: -11730.31 | D83: -29176.45 | E83: -14012.06 | F83: -9437.27 | G83: -10905.02 | H83: -18179.45 | I83: -14252.74 | J83: -13611.02 | K83: -14397.35
A84: Cash from Financing Activity | B84: -2579.36 | C84: 6639.94 | D84: -672.7 | E84: -1694.62 | F84: -37089.67 | G84: -23401.09 | H84: -6980.69 | I84: -11096.99 | J84: -7002.44 | K84: -21387.12
A85: Net Cash Flow | B85: -1244.65 | C85: 2933.02 | D85: -4513.2 | E85: 4462.04 | F85: -2200.26 | G85: 10074.88 | H85: -3477.06 | I85: -5049.06 | J85: 2524.12 | K85: -720.01
A90: PRICE: | B90: 45.99 | C90: 57.11 | D90: 52.1 | E90: 26.96 | F90: 81.19 | G90: 130.72 | H90: 104.5 | I90: 155.85 | J90: 154.24 | K90: 191.86
A92: DERIVED:
A93: Adjusted Equity Shares in Cr | B93: 1126.62 | C93: 1126.48 | D93: 1126.49 | E93: 1126.49 | F93: 1196.59 | G93: 1221.3 | H93: 1222.15 | I93: 1248.35 | J93: 1248.35 | K93: 1248.35
A96: Capitalisation | B96: =B93*B90 -> 51813.254 | C96: =C93*C90 -> 64333.273 | D96: =D93*D90 -> 58690.129 | E96: =E93*E90 -> 30370.17 | F96: =F93*F90 -> 97151.142 | G96: =G93*G90 -> 159648.34 | H96: =H93*H90 -> 127714.68 | I96: =I93*I90 -> 194555.35 | ... L96: =L93*L90 -> 0
A98: Debt | B98: =B59 -> 83014.49 | C98: =C59 -> 92147.05 | D98: =D59 -> 100816.22 | E98: =E59 -> 116328.2 | F98: =F59 -> 88501.41 | G98: =G59 -> 75561.35 | H98: =H59 -> 84893.05 | I98: =I59 -> 87082.12 | ... K98: =K59 -> 92381.68
A99: Cash | B99: =B69 -> 4921.05 | C99: =C69 -> 7937.85 | D99: =D69 -> 3341.37 | E99: =E69 -> 8054.72 | F99: =F69 -> 5782.18 | G99: =G69 -> 15898.93 | H99: =H69 -> 13357.26 | I99: =I69 -> 8677.72 | ... K99: =K69 -> 10057.53
A100: EV | B100: =B96+B98-B99 -> 129906.69 | C100: =C96+C98-C99 -> 148542.47 | D100: =D96+D98-D99 -> 156164.98 | E100: =E96+E98-E99 -> 138643.65 | F100: =F96+F98-F99 -> 179870.37 | G100: =G96+G98-G99 -> 219310.76 | H100: =H96+H98-H99 -> 199250.46 | I100: =I96+I98-I99 -> 272959.75 | ... K100: =K96+K98-K99 -> 321832.58
A102: EV/EBITDA | B102: =B100/'HistoricalFS '!C17 -> 9.8836238 | C102: =C100/'HistoricalFS '!D17 -> 6.9304883 | D102: =D100/'HistoricalFS '!E17 -> 5.3265505 | E102: =E100/'HistoricalFS '!F17 -> 7.9392529 | F102: =F100/'HistoricalFS '!G17 -> 5.8965657 | G102: =G100/'HistoricalFS '!H17 -> 3.4542594 | H102: =H100/'HistoricalFS '!I17 -> 6.1687145 | I102: =I100/'HistoricalFS '!J17 -> 12.269001 | ... K102: =K100/'HistoricalFS '!L17 -> 9.3685509
A103: EV/Sales | B103: =B100/B17 -> 1.1567886 | C103: =C100/C17 -> 1.2052219 | D103: =D100/D17 -> 0.99046096 | E103: =E100/E17 -> 0.99161044 | F103: =F100/F17 -> 1.1494974 | G103: =G100/G17 -> 0.898965 | H103: =H100/H17 -> 0.8187724 | I103: =I100/I17 -> 1.1910757 | ... K103: =K100/K17 -> 1.3863732
A104: Book Value | B104: =B57+B58 -> 37819.32 | C104: =C57+C58 -> 60870.62 | D104: =D57+D58 -> 68925.08 | E104: =E57+E58 -> 73576.3 | F104: =F57+F58 -> 74238.77 | G104: =G57+G58 -> 114443.04 | H104: =H57+H58 -> 103082.1 | I104: =I57+I58 -> 92035.76 | ... K104: =K57+K58 -> 102167.65
A106: P/B | B106: =B96/B104 -> 1.3700208 | C106: =C96/C104 -> 1.0568855 | D106: =D96/D104 -> 0.85150614 | E106: =E96/E104 -> 0.4127711 | F106: =F96/F104 -> 1.3086308 | G106: =G96/G104 -> 1.3950026 | H106: =H96/H104 -> 1.2389607 | I106: =I96/I104 -> 2.1139104 | ... K106: =K96/K104 -> 2.3442688
A108: P/E | B108: ='HistoricalFS '!C32/'Data Sheet'!B96 -> -0.0073236088 | C108: ='HistoricalFS '!D32/'Data Sheet'!C96 -> 0.10639005 | D108: ='HistoricalFS '!E32/'Data Sheet'!D96 -> 0.1294572 | E108: ='HistoricalFS '!F32/'Data Sheet'!E96 -> 0.13359425 | F108: ='HistoricalFS '!G32/'Data Sheet'!F96 -> 0.082448954 | G108: ='HistoricalFS '!H32/'Data Sheet'!G96 -> 0.25336518 | H108: ='HistoricalFS '!I32/'Data Sheet'!H96 -> 0.050945516 | I108: ='HistoricalFS '!J32/'Data Sheet'!I96 -> 0.0056314052 | ... K108: ='HistoricalFS '!L32/'Data Sheet'!K96 -> 0.042370116

Sheet HistoricalFS 
B2: ="Historical Financial Statement- "&'Data Sheet'!B1 -> Historical Financial Statement- TATA STEEL LTD
B3: Years | C3: ='Data Sheet'!B16 -> 42825 | D3: ='Data Sheet'!C16 -> 43190 | E3: ='Data Sheet'!D16 -> 43555 | F3: ='Data Sheet'!E16 -> 43921 | G3: ='Data Sheet'!F16 -> 44286 | H3: ='Data Sheet'!G16 -> 44651 | I3: ='Data Sheet'!H16 -> 45016 | J3: ='Data Sheet'!I16 -> 45382 | ... L3: ='Data Sheet'!K16 -> 46112 | M3: LTM
A4: # | B4: Income Statement
B5: Sales | C5: =IFERROR('Data Sheet'!B17,0) -> 112299.42 | D5: =IFERROR('Data Sheet'!C17,0) -> 123249.07 | E5: =IFERROR('Data Sheet'!D17,0) -> 157668.99 | F5: =IFERROR('Data Sheet'!E17,0) -> 139816.65 | G5: =IFERROR('Data Sheet'!F17,0) -> 156477.4 | H5: =IFERROR('Data Sheet'!G17,0) -> 243959.17 | I5: =IFERROR('Data Sheet'!H17,0) -> 243352.69 | J5: =IFERROR('Data Sheet'!I17,0) -> 229170.78 | ... L5: =IFERROR('Data Sheet'!K17,0) -> 232139.94 | M5: =IFERROR(SUM('Data Sheet'!H42:K42),0) -> 239756.11
B6: Sale Growth | C6: - | D6: =D5/C5-1 -> 0.097504065 | E6: =E5/D5-1 -> 0.27927124 | F6: =F5/E5-1 -> -0.1132267 | G6: =G5/F5-1 -> 0.11916142 | H6: =H5/G5-1 -> 0.55906968 | I6: =I5/H5-1 -> -0.0024859898 | J6: =J5/I5-1 -> -0.058277186 | K6: =K5/J5-1 -> -0.046377073 | ... M6: =M5/L5-1 -> 0.032808529
B8: COGS | C8: =IFERROR(SUM('Data Sheet'!B18,'Data Sheet'!B20:B22) -1*'Data Sheet'!B19,0) -> 77577.09 | D8: =IFERROR(SUM('Data Sheet'!C18,'Data Sheet'!C20:C22) -1*'Data Sheet'!C19,0) -> 84710.05 | E8: =IFERROR(SUM('Data Sheet'!D18,'Data Sheet'!D20:D22) -1*'Data Sheet'!D19,0) -> 105590.05 | F8: =IFERROR(SUM('Data Sheet'!E18,'Data Sheet'!E20:E22) -1*'Data Sheet'!E19,0) -> 102560.94 | G8: =IFERROR(SUM('Data Sheet'!F18,'Data Sheet'!F20:F22) -1*'Data Sheet'!F19,0) -> 102979.74 | H8: =IFERROR(SUM('Data Sheet'!G18,'Data Sheet'!G20:G22) -1*'Data Sheet'!G19,0) -> 143605.19 | I8: =IFERROR(SUM('Data Sheet'!H18,'Data Sheet'!H20:H22) -1*'Data Sheet'!H19,0) -> 178329.36 | J8: =IFERROR(SUM('Data Sheet'!I18,'Data Sheet'!I20:I22) -1*'Data Sheet'!I19,0) -> 183154.84 | ... L8: =IFERROR(SUM('Data Sheet'!K18,'Data Sheet'!K20:K22) -1*'Data Sheet'!K19,0) -> 171435.78 | M8: =IFERROR(SUM('Data Sheet'!H43:K43),0) -> 203566.87
B9: COGS % Sales | C9: =C8/C5 -> 0.69080579 | D9: =D8/D5 -> 0.68730782 | E9: =E8/E5 -> 0.66969447 | F9: =F8/F5 -> 0.73353882 | G9: =G8/G5 -> 0.65811255 | H9: =H8/H5 -> 0.58864436 | I9: =I8/I5 -> 0.73280209 | J9: =J8/J5 -> 0.79920677 | ... M9: =M8/M5 -> 0.84905811
B11: Gross Profit | C11: =IFERROR(C5-C8,0) -> 34722.33 | D11: =IFERROR(D5-D8,0) -> 38539.02 | E11: =IFERROR(E5-E8,0) -> 52078.94 | F11: =IFERROR(F5-F8,0) -> 37255.71 | G11: =IFERROR(G5-G8,0) -> 53497.66 | H11: =IFERROR(H5-H8,0) -> 100353.98 | I11: =IFERROR(I5-I8,0) -> 65023.33 | J11: =IFERROR(J5-J8,0) -> 46015.94 | ... M11: =IFERROR(M5-M8,0) -> 36189.24
B12: Gross Margin | C12: =IFERROR(C11/C5,0) -> 0.30919421 | D12: =IFERROR(D11/D5,0) -> 0.31269218 | E12: =IFERROR(E11/E5,0) -> 0.33030553 | F12: =IFERROR(F11/F5,0) -> 0.26646118 | G12: =IFERROR(G11/G5,0) -> 0.34188745 | H12: =IFERROR(H11/H5,0) -> 0.41135564 | I12: =IFERROR(I11/I5,0) -> 0.26719791 | J12: =IFERROR(J11/J5,0) -> 0.20079323 | ... M12: =IFERROR(M11/M5,0) -> 0.15094189
B14: Selling and General Expenses | C14: =IFERROR(SUM('Data Sheet'!B23:B24),0) -> 21578.7 | D14: =IFERROR(SUM('Data Sheet'!C23:C24),0) -> 17105.83 | E14: =IFERROR(SUM('Data Sheet'!D23:D24),0) -> 22760.72 | F14: =IFERROR(SUM('Data Sheet'!E23:E24),0) -> 19792.65 | G14: =IFERROR(SUM('Data Sheet'!F23:F24),0) -> 22993.4 | H14: =IFERROR(SUM('Data Sheet'!G23:G24),0) -> 36864.03 | I14: =IFERROR(SUM('Data Sheet'!H23:H24),0) -> 32723.17 | J14: =IFERROR(SUM('Data Sheet'!I23:I24),0) -> 23768.02 | ... M14: =IFERROR(SUM('Data Sheet'!L23:L24),0) -> 0
B15: S&G Exp % Sales | C15: =C14/C5 -> 0.19215326 | D15: =D14/D5 -> 0.13879074 | E15: =E14/E5 -> 0.14435762 | F15: =F14/F5 -> 0.14156147 | G15: =G14/G5 -> 0.1469439 | H15: =H14/H5 -> 0.15110738 | I15: =I14/I5 -> 0.13446808 | J15: =J14/J5 -> 0.10371313 | ... M15: =M14/M5 -> 0
B17: EBITDA | C17: =IFERROR(C11-C14,0) -> 13143.63 | D17: =IFERROR(D11-D14,0) -> 21433.19 | E17: =IFERROR(E11-E14,0) -> 29318.22 | F17: =IFERROR(F11-F14,0) -> 17463.06 | G17: =IFERROR(G11-G14,0) -> 30504.26 | H17: =IFERROR(H11-H14,0) -> 63489.95 | I17: =IFERROR(I11-I14,0) -> 32300.16 | J17: =IFERROR(J11-J14,0) -> 22247.92 | ... M17: =IFERROR(M11-M14,0) -> 36189.24
B18: EBITDA Margin | C18: =C17/C5 -> 0.11704094 | D18: =D17/D5 -> 0.17390143 | E18: =E17/E5 -> 0.18594792 | F18: =F17/F5 -> 0.12489972 | G18: =G17/G5 -> 0.19494355 | H18: =H17/H5 -> 0.26024826 | I18: =I17/I5 -> 0.13272983 | J18: =J17/J5 -> 0.09708009 | ... M18: =M17/M5 -> 0.15094189
B20: Interest | C20: =IFERROR('Data Sheet'!B27,0) -> 5072.2 | D20: =IFERROR('Data Sheet'!C27,0) -> 5454.74 | E20: =IFERROR('Data Sheet'!D27,0) -> 7660.1 | F20: =IFERROR('Data Sheet'!E27,0) -> 7533.46 | G20: =IFERROR('Data Sheet'!F27,0) -> 7606.71 | H20: =IFERROR('Data Sheet'!G27,0) -> 5462.2 | I20: =IFERROR('Data Sheet'!H27,0) -> 6298.7 | J20: =IFERROR('Data Sheet'!I27,0) -> 7507.57 | ... L20: =IFERROR('Data Sheet'!K27,0) -> 7167.06 | M20: =IFERROR(SUM('Data Sheet'!H46:K46),0) -> 7085.14
B21: Interest % Sales | C21: =C20/C5 -> 0.045166752 | D21: =D20/D5 -> 0.044257859 | E21: =E20/E5 -> 0.048583428 | F21: =F20/F5 -> 0.053880993 | G21: =G20/G5 -> 0.048612196 | H21: =H20/H5 -> 0.022389812 | I21: =I20/I5 -> 0.02588301 | J21: =J20/J5 -> 0.032759717 | ... M21: =M20/M5 -> 0.029551447
B23: Deprication | C23: =IFERROR('Data Sheet'!B26,0) -> 5672.88 | D23: =IFERROR('Data Sheet'!C26,0) -> 5741.7 | E23: =IFERROR('Data Sheet'!D26,0) -> 7341.83 | F23: =IFERROR('Data Sheet'!E26,0) -> 8440.73 | G23: =IFERROR('Data Sheet'!F26,0) -> 9233.64 | H23: =IFERROR('Data Sheet'!G26,0) -> 9100.87 | I23: =IFERROR('Data Sheet'!H26,0) -> 9335.2 | J23: =IFERROR('Data Sheet'!I26,0) -> 9882.16 | ... L23: =IFERROR('Data Sheet'!K26,0) -> 11954.51 | M23: =IFERROR(SUM('Data Sheet'!H45:K45),0) -> 12849.86
B24: Deprication % Sales | C24: =C23/C5 -> 0.050515666 | D24: =D23/D5 -> 0.046586153 | E24: =E23/E5 -> 0.046564832 | F24: =F23/F5 -> 0.060369992 | G24: =G23/G5 -> 0.059009416 | H24: =H23/H5 -> 0.03730489 | I24: =I23/I5 -> 0.038360784 | J24: =J23/J5 -> 0.043121379 | ... M24: =M23/M5 -> 0.053595548
B26: EBT/ Profit | C26: =IFERROR(C17-SUM(C20,C23),0) -> 2398.55 | D26: =IFERROR(D17-SUM(D20,D23),0) -> 10236.75 | E26: =IFERROR(E17-SUM(E20,E23),0) -> 14316.29 | F26: =IFERROR(F17-SUM(F20,F23),0) -> 1488.87 | G26: =IFERROR(G17-SUM(G20,G23),0) -> 13663.91 | H26: =IFERROR(H17-SUM(H20,H23),0) -> 48926.88 | I26: =IFERROR(I17-SUM(I20,I23),0) -> 16666.26 | J26: =IFERROR(J17-SUM(J20,J23),0) -> 4858.19 | ... M26: =IFERROR(M17-SUM(M20,M23),0) -> 16254.24
B27: EBT % Sales | C27: =C26/C5 -> 0.021358525 | D27: =D26/D5 -> 0.083057422 | E27: =E26/E5 -> 0.090799656 | F27: =F26/F5 -> 0.010648732 | G27: =G26/G5 -> 0.087321939 | H27: =H26/H5 -> 0.20055356 | I27: =I26/I5 -> 0.068486032 | J27: =J26/J5 -> 0.021198994 | ... M27: =M26/M5 -> 0.067794894
B29: Tax | C29: =IFERROR('Data Sheet'!B29,0) -> 2778.01 | D29: =IFERROR('Data Sheet'!C29,0) -> 3392.33 | E29: =IFERROR('Data Sheet'!D29,0) -> 6718.43 | F29: =IFERROR('Data Sheet'!E29,0) -> -2568.41 | G29: =IFERROR('Data Sheet'!F29,0) -> 5653.9 | H29: =IFERROR('Data Sheet'!G29,0) -> 8477.55 | I29: =IFERROR('Data Sheet'!H29,0) -> 10159.77 | J29: =IFERROR('Data Sheet'!I29,0) -> 3762.57 | ... L29: =IFERROR('Data Sheet'!K29,0) -> 5082.87 | M29: =IFERROR(SUM('Data Sheet'!H48:K48),0) -> 5475.44
B30: Effective Tax Rate | C30: =C29/C26 -> 1.1582039 | D30: =D29/D26 -> 0.3313874 | E30: =E29/E26 -> 0.46928569 | F30: =F29/F26 -> -1.7250734 | G30: =G29/G26 -> 0.41378346 | H30: =H29/H26 -> 0.17326979 | I30: =I29/I26 -> 0.60960107 | J30: =J29/J26 -> 0.7744798 | ... M30: =M29/M26 -> 0.33686226
B32: Net Profit | C32: =IFERROR(C26-C29,0) -> -379.46 | D32: =IFERROR(D26-D29,0) -> 6844.42 | E32: =IFERROR(E26-E29,0) -> 7597.86 | F32: =IFERROR(F26-F29,0) -> 4057.28 | G32: =IFERROR(G26-G29,0) -> 8010.01 | H32: =IFERROR(H26-H29,0) -> 40449.33 | I32: =IFERROR(I26-I29,0) -> 6506.49 | J32: =IFERROR(J26-J29,0) -> 1095.62 | ... M32: =IFERROR(M26-M29,0) -> 10778.8
B33: Net margin | C33: =C32/C5 -> -0.0033790023 | D33: =D32/D5 -> 0.055533239 | E33: =E32/E5 -> 0.048188677 | F33: =F32/F5 -> 0.029018575 | G33: =G32/G5 -> 0.051189565 | H33: =H32/H5 -> 0.16580369 | I33: =I32/I5 -> 0.026736873 | J33: =J32/J5 -> 0.0047808015 | ... M33: =M32/M5 -> 0.044957353
B35: No. of Equity Shares | C35: =IFERROR('Data Sheet'!B93,0) -> 1126.62 | D35: =IFERROR('Data Sheet'!C93,0) -> 1126.48 | E35: =IFERROR('Data Sheet'!D93,0) -> 1126.49 | F35: =IFERROR('Data Sheet'!E93,0) -> 1126.49 | G35: =IFERROR('Data Sheet'!F93,0) -> 1196.59 | H35: =IFERROR('Data Sheet'!G93,0) -> 1221.3 | I35: =IFERROR('Data Sheet'!H93,0) -> 1222.15 | J35: =IFERROR('Data Sheet'!I93,0) -> 1248.35 | ... M35: =IFERROR('Data Sheet'!L93,0) -> 0
B37: Earning Per Share | C37: =IFERROR(C32/C35,0) -> -0.33681277 | D37: =IFERROR(D32/D35,0) -> 6.0759357 | E37: =IFERROR(E32/E35,0) -> 6.7447203 | F37: =IFERROR(F32/F35,0) -> 3.6017009 | G37: =IFERROR(G32/G35,0) -> 6.6940305 | H37: =IFERROR(H32/H35,0) -> 33.119897 | I37: =IFERROR(I32/I35,0) -> 5.3238064 | J37: =IFERROR(J32/J35,0) -> 0.8776545 | ... M37: =IFERROR(M32/M35,0) -> 0
B38: Earning Growth % | D38: =IFERROR(D37/-C37-1,0) -> 17.039505 | E38: =IFERROR(E37/D37-1,0) -> 0.11007106 | F38: =IFERROR(F37/E37-1,0) -> -0.465997 | G38: =IFERROR(G37/F37-1,0) -> 0.85857482 | H38: =IFERROR(H37/G37-1,0) -> 3.9476764 | I38: =IFERROR(I37/H37-1,0) -> -0.83925655 | J38: =IFERROR(J37/I37-1,0) -> -0.8351453 | K38: =IFERROR(K37/J37-1,0) -> 1.0966028 | L38: =IFERROR(L37/K37-1,0) -> 3.4177826
B40: Dividend Per Share | C40: =IFERROR('Data Sheet'!B31/'HistoricalFS '!C35,0) -> 0.86119543 | D40: =IFERROR('Data Sheet'!C31/'HistoricalFS '!D35,0) -> 1.0163962 | E40: =IFERROR('Data Sheet'!D31/'HistoricalFS '!E35,0) -> 1.32129 | F40: =IFERROR('Data Sheet'!E31/'HistoricalFS '!F35,0) -> 1.0163872 | G40: =IFERROR('Data Sheet'!F31/'HistoricalFS '!G35,0) -> 2.5021269 | H40: =IFERROR('Data Sheet'!G31/'HistoricalFS '!H35,0) -> 5.0996234 | I40: =IFERROR('Data Sheet'!H31/'HistoricalFS '!I35,0) -> 3.5973162 | J40: =IFERROR('Data Sheet'!I31/'HistoricalFS '!J35,0) -> 3.5973725 | ... N40: =IFERROR('Data Sheet'!M31/'HistoricalFS '!N35,0) -> 0
B41: Dividend Payout Ratio | C41: =IFERROR(C40/-C37,0) -> 2.5568966 | D41: =IFERROR(D40/D37,0) -> 0.16728225 | E41: =IFERROR(E40/E37,0) -> 0.1958999 | F41: =IFERROR(F40/F37,0) -> 0.28219645 | G41: =IFERROR(G40/G37,0) -> 0.3737848 | H41: =IFERROR(H40/H37,0) -> 0.15397461 | I41: =IFERROR(I40/I37,0) -> 0.6757038 | J41: =IFERROR(J40/J37,0) -> 4.0988481 | K41: =IFERROR(K40/K37,0) -> 1.954995 | ... M41: =IFERROR(M40/M37,0) -> 0
B43: Reatined Earning | C43: =IFERROR(IF(C37>C40,1-C41,0),0) -> 0 | D43: =IFERROR(IF(D37>D40,1-D41,0),0) -> 0.83271775 | E43: =IFERROR(IF(E37>E40,1-E41,0),0) -> 0.8041001 | F43: =IFERROR(IF(F37>F40,1-F41,0),0) -> 0.71780355 | G43: =IFERROR(IF(G37>G40,1-G41,0),0) -> 0.6262152 | H43: =IFERROR(IF(H37>H40,1-H41,0),0) -> 0.84602539 | I43: =IFERROR(IF(I37>I40,1-I41,0),0) -> 0.3242962 | J43: =IFERROR(IF(J37>J40,1-J41,0),0) -> 0 | ... M43: =IFERROR(IF(M37>M40,1-M41,0),0) -> 0
A47: # | B47: Balance Sheet
B48: Equity Share Capital | C48: =IFERROR('Data Sheet'!B57,0) -> 970.24 | D48: =IFERROR('Data Sheet'!C57,0) -> 1144.95 | E48: =IFERROR('Data Sheet'!D57,0) -> 1144.94 | F48: =IFERROR('Data Sheet'!E57,0) -> 1144.95 | G48: =IFERROR('Data Sheet'!F57,0) -> 1197.61 | H48: =IFERROR('Data Sheet'!G57,0) -> 1221.21 | I48: =IFERROR('Data Sheet'!H57,0) -> 1221.24 | J48: =IFERROR('Data Sheet'!I57,0) -> 1247.44 | ... L48: =IFERROR('Data Sheet'!K57,0) -> 1247.44
B49: Reserves | C49: =IFERROR('Data Sheet'!B58,0) -> 36849.08 | D49: =IFERROR('Data Sheet'!C58,0) -> 59725.67 | E49: =IFERROR('Data Sheet'!D58,0) -> 67780.14 | F49: =IFERROR('Data Sheet'!E58,0) -> 72431.35 | G49: =IFERROR('Data Sheet'!F58,0) -> 73041.16 | H49: =IFERROR('Data Sheet'!G58,0) -> 113221.83 | I49: =IFERROR('Data Sheet'!H58,0) -> 101860.86 | J49: =IFERROR('Data Sheet'!I58,0) -> 90788.32 | ... L49: =IFERROR('Data Sheet'!K58,0) -> 100920.21
B50: Borrowings | C50: =IFERROR('Data Sheet'!B59,0) -> 83014.49 | D50: =IFERROR('Data Sheet'!C59,0) -> 92147.05 | E50: =IFERROR('Data Sheet'!D59,0) -> 100816.22 | F50: =IFERROR('Data Sheet'!E59,0) -> 116328.2 | G50: =IFERROR('Data Sheet'!F59,0) -> 88501.41 | H50: =IFERROR('Data Sheet'!G59,0) -> 75561.35 | I50: =IFERROR('Data Sheet'!H59,0) -> 84893.05 | J50: =IFERROR('Data Sheet'!I59,0) -> 87082.12 | ... L50: =IFERROR('Data Sheet'!K59,0) -> 92381.68
B51: Other Liabilities | C51: =IFERROR('Data Sheet'!B60,0) -> 51613.56 | D51: =IFERROR('Data Sheet'!C60,0) -> 55704.47 | E51: =IFERROR('Data Sheet'!D60,0) -> 63032.14 | F51: =IFERROR('Data Sheet'!E60,0) -> 59244.62 | G51: =IFERROR('Data Sheet'!F60,0) -> 81169.01 | H51: =IFERROR('Data Sheet'!G60,0) -> 92417.28 | I51: =IFERROR('Data Sheet'!H60,0) -> 97420.63 | J51: =IFERROR('Data Sheet'!I60,0) -> 90194.54 | ... L51: =IFERROR('Data Sheet'!K60,0) -> 101965.29
B52: Total Liabilities | C52: =IFERROR('Data Sheet'!B61,0) -> 172447.37 | D52: =IFERROR('Data Sheet'!C61,0) -> 208722.14 | E52: =IFERROR('Data Sheet'!D61,0) -> 232773.44 | F52: =IFERROR('Data Sheet'!E61,0) -> 249149.12 | G52: =IFERROR('Data Sheet'!F61,0) -> 243909.19 | H52: =IFERROR('Data Sheet'!G61,0) -> 282421.67 | I52: =IFERROR('Data Sheet'!H61,0) -> 285395.78 | J52: =IFERROR('Data Sheet'!I61,0) -> 269312.42 | ... L52: =IFERROR('Data Sheet'!K61,0) -> 296514.62
B54: Net Block | C54: =IFERROR('Data Sheet'!B62,0) -> 92006.55 | D54: =IFERROR('Data Sheet'!C62,0) -> 96104.89 | E54: =IFERROR('Data Sheet'!D62,0) -> 124441.91 | F54: =IFERROR('Data Sheet'!E62,0) -> 134550.66 | G54: =IFERROR('Data Sheet'!F62,0) -> 135775.18 | H54: =IFERROR('Data Sheet'!G62,0) -> 133287.83 | I54: =IFERROR('Data Sheet'!H62,0) -> 146621.46 | J54: =IFERROR('Data Sheet'!I62,0) -> 148814.38 | ... L54: =IFERROR('Data Sheet'!K62,0) -> 179908.13
B55: Capital Work in Progress | C55: =IFERROR('Data Sheet'!B63,0) -> 15784.13 | D55: =IFERROR('Data Sheet'!C63,0) -> 16614.41 | E55: =IFERROR('Data Sheet'!D63,0) -> 18641.21 | F55: =IFERROR('Data Sheet'!E63,0) -> 19496.83 | G55: =IFERROR('Data Sheet'!F63,0) -> 19007.4 | H55: =IFERROR('Data Sheet'!G63,0) -> 22045.55 | I55: =IFERROR('Data Sheet'!H63,0) -> 31213.02 | J55: =IFERROR('Data Sheet'!I63,0) -> 34355.53 | ... L55: =IFERROR('Data Sheet'!K63,0) -> 28496.71
B56: Investments | C56: =IFERROR('Data Sheet'!B64,0) -> 12457.12 | D56: =IFERROR('Data Sheet'!C64,0) -> 17899.47 | E56: =IFERROR('Data Sheet'!D64,0) -> 5738.17 | F56: =IFERROR('Data Sheet'!E64,0) -> 6285.18 | G56: =IFERROR('Data Sheet'!F64,0) -> 10681.93 | H56: =IFERROR('Data Sheet'!G64,0) -> 13139.85 | I56: =IFERROR('Data Sheet'!H64,0) -> 8410.31 | J56: =IFERROR('Data Sheet'!I64,0) -> 6257.57 | ... L56: =IFERROR('Data Sheet'!K64,0) -> 7088.85
B57: Other Assets | C57: =IFERROR(SUM('Data Sheet'!B65)-SUM('Data Sheet'!B67:B69),0) -> 10887.88 | D57: =IFERROR(SUM('Data Sheet'!C65)-SUM('Data Sheet'!C67:C69),0) -> 29418.96 | E57: =IFERROR(SUM('Data Sheet'!D65)-SUM('Data Sheet'!D67:D69),0) -> 37143.68 | F57: =IFERROR(SUM('Data Sheet'!E65)-SUM('Data Sheet'!E67:E69),0) -> 41808.1 | G57: =IFERROR(SUM('Data Sheet'!F65)-SUM('Data Sheet'!F67:F69),0) -> 29846.28 | H57: =IFERROR(SUM('Data Sheet'!G65)-SUM('Data Sheet'!G67:G69),0) -> 36978.69 | I57: =IFERROR(SUM('Data Sheet'!H65)-SUM('Data Sheet'!H67:H69),0) -> 23121.16 | J57: =IFERROR(SUM('Data Sheet'!I65)-SUM('Data Sheet'!I67:I69),0) -> 15786.18 | ... L57: =IFERROR(SUM('Data Sheet'!K65)-SUM('Data Sheet'!K67:K69),0) -> 18797.29
B58: Total Non-Current Assets | C58: =IFERROR(SUM(C54:C57),0) -> 131135.68 | D58: =IFERROR(SUM(D54:D57),0) -> 160037.73 | E58: =IFERROR(SUM(E54:E57),0) -> 185964.97 | F58: =IFERROR(SUM(F54:F57),0) -> 202140.77 | G58: =IFERROR(SUM(G54:G57),0) -> 195310.79 | H58: =IFERROR(SUM(H54:H57),0) -> 205451.92 | I58: =IFERROR(SUM(I54:I57),0) -> 209365.95 | J58: =IFERROR(SUM(J54:J57),0) -> 205213.66 | ... L58: =IFERROR(SUM(L54:L57),0) -> 234290.98
B60: Receivables | C60: =IFERROR('Data Sheet'!B67,0) -> 11586.82 | D60: =IFERROR('Data Sheet'!C67,0) -> 12415.52 | E60: =IFERROR('Data Sheet'!D67,0) -> 11811 | F60: =IFERROR('Data Sheet'!E67,0) -> 7884.91 | G60: =IFERROR('Data Sheet'!F67,0) -> 9539.84 | H60: =IFERROR('Data Sheet'!G67,0) -> 12246.43 | I60: =IFERROR('Data Sheet'!H67,0) -> 8257.24 | J60: =IFERROR('Data Sheet'!I67,0) -> 6263.53 | ... L60: =IFERROR('Data Sheet'!K67,0) -> 4916.89
B61: Inventory | C61: =IFERROR('Data Sheet'!B68,0) -> 24803.82 | D61: =IFERROR('Data Sheet'!C68,0) -> 28331.04 | E61: =IFERROR('Data Sheet'!D68,0) -> 31656.1 | F61: =IFERROR('Data Sheet'!E68,0) -> 31068.72 | G61: =IFERROR('Data Sheet'!F68,0) -> 33276.38 | H61: =IFERROR('Data Sheet'!G68,0) -> 48824.39 | I61: =IFERROR('Data Sheet'!H68,0) -> 54415.33 | J61: =IFERROR('Data Sheet'!I68,0) -> 49157.51 | ... L61: =IFERROR('Data Sheet'!K68,0) -> 47249.22
B62: Cash & Bank | C62: =IFERROR('Data Sheet'!B69,0) -> 4921.05 | D62: =IFERROR('Data Sheet'!C69,0) -> 7937.85 | E62: =IFERROR('Data Sheet'!D69,0) -> 3341.37 | F62: =IFERROR('Data Sheet'!E69,0) -> 8054.72 | G62: =IFERROR('Data Sheet'!F69,0) -> 5782.18 | H62: =IFERROR('Data Sheet'!G69,0) -> 15898.93 | I62: =IFERROR('Data Sheet'!H69,0) -> 13357.26 | J62: =IFERROR('Data Sheet'!I69,0) -> 8677.72 | ... L62: =IFERROR('Data Sheet'!K69,0) -> 10057.53
B63: Total Current Assets | C63: =IFERROR(SUM(C60:C62),0) -> 41311.69 | D63: =IFERROR(SUM(D60:D62),0) -> 48684.41 | E63: =IFERROR(SUM(E60:E62),0) -> 46808.47 | F63: =IFERROR(SUM(F60:F62),0) -> 47008.35 | G63: =IFERROR(SUM(G60:G62),0) -> 48598.4 | H63: =IFERROR(SUM(H60:H62),0) -> 76969.75 | I63: =IFERROR(SUM(I60:I62),0) -> 76029.83 | J63: =IFERROR(SUM(J60:J62),0) -> 64098.76 | ... L63: =IFERROR(SUM(L60:L62),0) -> 62223.64
B65: Total Assets | C65: =IFERROR(SUM(C58,C63),0) -> 172447.37 | D65: =IFERROR(SUM(D58,D63),0) -> 208722.14 | E65: =IFERROR(SUM(E58,E63),0) -> 232773.44 | F65: =IFERROR(SUM(F58,F63),0) -> 249149.12 | G65: =IFERROR(SUM(G58,G63),0) -> 243909.19 | H65: =IFERROR(SUM(H58,H63),0) -> 282421.67 | I65: =IFERROR(SUM(I58,I63),0) -> 285395.78 | J65: =IFERROR(SUM(J58,J63),0) -> 269312.42 | ... L65: =IFERROR(SUM(L58,L63),0) -> 296514.62
A68: # | B68: Cash Flow Statement
B69: Operating Activities
B70: Profit from operations | C70: =IFERROR('Cash Flow Data'!E4,0) -> 17581 | D70: =IFERROR('Cash Flow Data'!F4,0) -> 20187 | E70: =IFERROR('Cash Flow Data'!G4,0) -> 27840 | F70: =IFERROR('Cash Flow Data'!H4,0) -> 18078 | G70: =IFERROR('Cash Flow Data'!I4,0) -> 28540 | H70: =IFERROR('Cash Flow Data'!J4,0) -> 65900 | I70: =IFERROR('Cash Flow Data'!K4,0) -> 30908 | J70: =IFERROR('Cash Flow Data'!L4,0) -> 22237 | ... L70: =IFERROR('Cash Flow Data'!N4,0) -> 34219
B71: Receivables | C71: =IFERROR('Cash Flow Data'!E5,0) -> 0 | D71: =IFERROR('Cash Flow Data'!F5,0) -> 0 | E71: =IFERROR('Cash Flow Data'!G5,0) -> 0 | F71: =IFERROR('Cash Flow Data'!H5,0) -> 0 | G71: =IFERROR('Cash Flow Data'!I5,0) -> 0 | H71: =IFERROR('Cash Flow Data'!J5,0) -> 0 | I71: =IFERROR('Cash Flow Data'!K5,0) -> 0 | J71: =IFERROR('Cash Flow Data'!L5,0) -> 0 | ... L71: =IFERROR('Cash Flow Data'!N5,0) -> 0
B72: Inventory | C72: =IFERROR('Cash Flow Data'!E6,0) -> -8243 | D72: =IFERROR('Cash Flow Data'!F6,0) -> -1595 | E72: =IFERROR('Cash Flow Data'!G6,0) -> -1069 | F72: =IFERROR('Cash Flow Data'!H6,0) -> 1562 | G72: =IFERROR('Cash Flow Data'!I6,0) -> 46 | H72: =IFERROR('Cash Flow Data'!J6,0) -> -16917 | I72: =IFERROR('Cash Flow Data'!K6,0) -> -4031 | J72: =IFERROR('Cash Flow Data'!L6,0) -> 5566 | ... L72: =IFERROR('Cash Flow Data'!N6,0) -> 1290
B73: Payables | C73: =IFERROR('Cash Flow Data'!E7,0) -> 0 | D73: =IFERROR('Cash Flow Data'!F7,0) -> 0 | E73: =IFERROR('Cash Flow Data'!G7,0) -> 0 | F73: =IFERROR('Cash Flow Data'!H7,0) -> 0 | G73: =IFERROR('Cash Flow Data'!I7,0) -> 0 | H73: =IFERROR('Cash Flow Data'!J7,0) -> 0 | I73: =IFERROR('Cash Flow Data'!K7,0) -> 0 | J73: =IFERROR('Cash Flow Data'!L7,0) -> 0 | ... L73: =IFERROR('Cash Flow Data'!N7,0) -> 0
B74: Other WC items | C74: =IFERROR('Cash Flow Data'!E8,0) -> 3329 | D74: =IFERROR('Cash Flow Data'!F8,0) -> -7680 | E74: =IFERROR('Cash Flow Data'!G8,0) -> 3659 | F74: =IFERROR('Cash Flow Data'!H8,0) -> 2634 | G74: =IFERROR('Cash Flow Data'!I8,0) -> 16446 | H74: =IFERROR('Cash Flow Data'!J8,0) -> 7299 | I74: =IFERROR('Cash Flow Data'!K8,0) -> 325 | J74: =IFERROR('Cash Flow Data'!L8,0) -> -2182 | ... L74: =IFERROR('Cash Flow Data'!N8,0) -> 4152
B75: Working capital changes | C75: =IFERROR('Cash Flow Data'!E9,0) -> -4914 | D75: =IFERROR('Cash Flow Data'!F9,0) -> -9276 | E75: =IFERROR('Cash Flow Data'!G9,0) -> 2591 | F75: =IFERROR('Cash Flow Data'!H9,0) -> 4196 | G75: =IFERROR('Cash Flow Data'!I9,0) -> 16491 | H75: =IFERROR('Cash Flow Data'!J9,0) -> -9618 | I75: =IFERROR('Cash Flow Data'!K9,0) -> -3706 | J75: =IFERROR('Cash Flow Data'!L9,0) -> 3384 | ... L75: =IFERROR('Cash Flow Data'!N9,0) -> 5442
B76: Direct taxes | C76: =IFERROR('Cash Flow Data'!E10,0) -> -1843 | D76: =IFERROR('Cash Flow Data'!F10,0) -> -2888 | E76: =IFERROR('Cash Flow Data'!G10,0) -> -5094 | F76: =IFERROR('Cash Flow Data'!H10,0) -> -2106 | G76: =IFERROR('Cash Flow Data'!I10,0) -> -704 | H76: =IFERROR('Cash Flow Data'!J10,0) -> -11902 | I76: =IFERROR('Cash Flow Data'!K10,0) -> -5519 | J76: =IFERROR('Cash Flow Data'!L10,0) -> -5320 | ... L76: =IFERROR('Cash Flow Data'!N10,0) -> -4597
B77: Cash From Opeating Activites | C77: =IFERROR(SUM(C70:C76),0) -> 5910 | D77: =IFERROR(SUM(D70:D76),0) -> -1252 | E77: =IFERROR(SUM(E70:E76),0) -> 27927 | F77: =IFERROR(SUM(F70:F76),0) -> 24364 | G77: =IFERROR(SUM(G70:G76),0) -> 60819 | H77: =IFERROR(SUM(H70:H76),0) -> 34762 | I77: =IFERROR(SUM(I70:I76),0) -> 17977 | J77: =IFERROR(SUM(J70:J76),0) -> 23685 | ... L77: =IFERROR(SUM(L70:L76),0) -> 40506
B79: Investing Activites
B80: Fixed assets purchased | C80: =IFERROR('Cash Flow Data'!E12,0) -> -7716 | D80: =IFERROR('Cash Flow Data'!F12,0) -> -7478 | E80: =IFERROR('Cash Flow Data'!G12,0) -> -9091 | F80: =IFERROR('Cash Flow Data'!H12,0) -> -10398 | G80: =IFERROR('Cash Flow Data'!I12,0) -> -6979 | H80: =IFERROR('Cash Flow Data'!J12,0) -> -10522 | I80: =IFERROR('Cash Flow Data'!K12,0) -> -14142 | J80: =IFERROR('Cash Flow Data'!L12,0) -> -18207 | ... L80: =IFERROR('Cash Flow Data'!N12,0) -> -14559
B81: Fixed assets sold | C81: =IFERROR('Cash Flow Data'!E13,0) -> 289 | D81: =IFERROR('Cash Flow Data'!F13,0) -> 179 | E81: =IFERROR('Cash Flow Data'!G13,0) -> 467 | F81: =IFERROR('Cash Flow Data'!H13,0) -> 386 | G81: =IFERROR('Cash Flow Data'!I13,0) -> 445 | H81: =IFERROR('Cash Flow Data'!J13,0) -> 569 | I81: =IFERROR('Cash Flow Data'!K13,0) -> 328 | J81: =IFERROR('Cash Flow Data'!L13,0) -> 475 | ... L81: =IFERROR('Cash Flow Data'!N13,0) -> 1401
B82: Investments purchased | C82: =IFERROR('Cash Flow Data'!E14,0) -> -861 | D82: =IFERROR('Cash Flow Data'!F14,0) -> -8641 | E82: =IFERROR('Cash Flow Data'!G14,0) -> -490 | F82: =IFERROR('Cash Flow Data'!H14,0) -> -828 | G82: =IFERROR('Cash Flow Data'!I14,0) -> -3631 | H82: =IFERROR('Cash Flow Data'!J14,0) -> -1153 | I82: =IFERROR('Cash Flow Data'!K14,0) -> -326 | J82: =IFERROR('Cash Flow Data'!L14,0) -> -4 | ... L82: =IFERROR('Cash Flow Data'!N14,0) -> -553
B83: Investments sold | C83: =IFERROR('Cash Flow Data'!E15,0) -> 91 | D83: =IFERROR('Cash Flow Data'!F15,0) -> 3899 | E83: =IFERROR('Cash Flow Data'!G15,0) -> 13556 | F83: =IFERROR('Cash Flow Data'!H15,0) -> 121 | G83: =IFERROR('Cash Flow Data'!I15,0) -> 0 | H83: =IFERROR('Cash Flow Data'!J15,0) -> 63 | I83: =IFERROR('Cash Flow Data'!K15,0) -> 5191 | J83: =IFERROR('Cash Flow Data'!L15,0) -> 3171 | ... L83: =IFERROR('Cash Flow Data'!N15,0) -> 20
B84: Interest received | C84: =IFERROR('Cash Flow Data'!E16,0) -> 140 | D84: =IFERROR('Cash Flow Data'!F16,0) -> 254 | E84: =IFERROR('Cash Flow Data'!G16,0) -> 175 | F84: =IFERROR('Cash Flow Data'!H16,0) -> 203 | G84: =IFERROR('Cash Flow Data'!I16,0) -> 266 | H84: =IFERROR('Cash Flow Data'!J16,0) -> 137 | I84: =IFERROR('Cash Flow Data'!K16,0) -> 248 | J84: =IFERROR('Cash Flow Data'!L16,0) -> 333 | ... L84: =IFERROR('Cash Flow Data'!N16,0) -> 650
B85: Dividends received | C85: =IFERROR('Cash Flow Data'!E17,0) -> 85 | D85: =IFERROR('Cash Flow Data'!F17,0) -> 111 | E85: =IFERROR('Cash Flow Data'!G17,0) -> 148 | F85: =IFERROR('Cash Flow Data'!H17,0) -> 103 | G85: =IFERROR('Cash Flow Data'!I17,0) -> 135 | H85: =IFERROR('Cash Flow Data'!J17,0) -> 162 | I85: =IFERROR('Cash Flow Data'!K17,0) -> 317 | J85: =IFERROR('Cash Flow Data'!L17,0) -> 336 | ... L85: =IFERROR('Cash Flow Data'!N17,0) -> 408
B86: Redemp n Canc of Shares | C86: =IFERROR('Cash Flow Data'!E18,0) -> 0 | D86: =IFERROR('Cash Flow Data'!F18,0) -> 34 | E86: =IFERROR('Cash Flow Data'!G18,0) -> 156 | F86: =IFERROR('Cash Flow Data'!H18,0) -> 378 | G86: =IFERROR('Cash Flow Data'!I18,0) -> 90 | H86: =IFERROR('Cash Flow Data'!J18,0) -> 1208 | I86: =IFERROR('Cash Flow Data'!K18,0) -> 166 | J86: =IFERROR('Cash Flow Data'!L18,0) -> 123 | ... L86: =IFERROR('Cash Flow Data'!N18,0) -> 611
B87: Acquisition of companies | C87: =IFERROR('Cash Flow Data'!E19,0) -> -1081 | D87: =IFERROR('Cash Flow Data'!F19,0) -> -255 | E87: =IFERROR('Cash Flow Data'!G19,0) -> -34569 | F87: =IFERROR('Cash Flow Data'!H19,0) -> -4433 | G87: =IFERROR('Cash Flow Data'!I19,0) -> 0 | H87: =IFERROR('Cash Flow Data'!J19,0) -> -53 | I87: =IFERROR('Cash Flow Data'!K19,0) -> -10569 | J87: =IFERROR('Cash Flow Data'!L19,0) -> 0 | ... L87: =IFERROR('Cash Flow Data'!N19,0) -> -2846
B88: Inter corporate deposits | C88: =IFERROR('Cash Flow Data'!E20,0) -> 0 | D88: =IFERROR('Cash Flow Data'!F20,0) -> 0 | E88: =IFERROR('Cash Flow Data'!G20,0) -> 0 | F88: =IFERROR('Cash Flow Data'!H20,0) -> 0 | G88: =IFERROR('Cash Flow Data'!I20,0) -> 0 | H88: =IFERROR('Cash Flow Data'!J20,0) -> 0 | I88: =IFERROR('Cash Flow Data'!K20,0) -> 0 | J88: =IFERROR('Cash Flow Data'!L20,0) -> 0 | ... L88: =IFERROR('Cash Flow Data'!N20,0) -> 0
B89: Other investing items | C89: =IFERROR('Cash Flow Data'!E21,0) -> -437 | D89: =IFERROR('Cash Flow Data'!F21,0) -> 166 | E89: =IFERROR('Cash Flow Data'!G21,0) -> 471 | F89: =IFERROR('Cash Flow Data'!H21,0) -> 456 | G89: =IFERROR('Cash Flow Data'!I21,0) -> 236 | H89: =IFERROR('Cash Flow Data'!J21,0) -> -1315 | I89: =IFERROR('Cash Flow Data'!K21,0) -> 609 | J89: =IFERROR('Cash Flow Data'!L21,0) -> -481 | ... L89: =IFERROR('Cash Flow Data'!N21,0) -> 472
B90: Cash From Investing Activites | C90: =IFERROR(SUM(C80:C89),0) -> -9490 | D90: =IFERROR(SUM(D80:D89),0) -> -11731 | E90: =IFERROR(SUM(E80:E89),0) -> -29177 | F90: =IFERROR(SUM(F80:F89),0) -> -14012 | G90: =IFERROR(SUM(G80:G89),0) -> -9438 | H90: =IFERROR(SUM(H80:H89),0) -> -10904 | I90: =IFERROR(SUM(I80:I89),0) -> -18178 | J90: =IFERROR(SUM(J80:J89),0) -> -14254 | ... L90: =IFERROR(SUM(L80:L89),0) -> -14396
B92: Financing Activites
B93: Proceeds from shares | C93: =IFERROR('Cash Flow Data'!E23,0) -> 652 | D93: =IFERROR('Cash Flow Data'!F23,0) -> 9087 | E93: =IFERROR('Cash Flow Data'!G23,0) -> 0 | F93: =IFERROR('Cash Flow Data'!H23,0) -> 188 | G93: =IFERROR('Cash Flow Data'!I23,0) -> 3239 | H93: =IFERROR('Cash Flow Data'!J23,0) -> 326 | I93: =IFERROR('Cash Flow Data'!K23,0) -> 1 | J93: =IFERROR('Cash Flow Data'!L23,0) -> 0 | ... L93: =IFERROR('Cash Flow Data'!N23,0) -> 0
B94: Proceeds from borrowings | C94: =IFERROR('Cash Flow Data'!E24,0) -> 0 | D94: =IFERROR('Cash Flow Data'!F24,0) -> 0 | E94: =IFERROR('Cash Flow Data'!G24,0) -> 33344 | F94: =IFERROR('Cash Flow Data'!H24,0) -> 16574 | G94: =IFERROR('Cash Flow Data'!I24,0) -> 9801 | H94: =IFERROR('Cash Flow Data'!J24,0) -> 12439 | I94: =IFERROR('Cash Flow Data'!K24,0) -> 16769 | J94: =IFERROR('Cash Flow Data'!L24,0) -> 14120 | ... L94: =IFERROR('Cash Flow Data'!N24,0) -> 15954
B95: Repayment of borrowings | C95: =IFERROR('Cash Flow Data'!E25,0) -> 0 | D95: =IFERROR('Cash Flow Data'!F25,0) -> 0 | E95: =IFERROR('Cash Flow Data'!G25,0) -> -25077 | F95: =IFERROR('Cash Flow Data'!H25,0) -> -7937 | G95: =IFERROR('Cash Flow Data'!I25,0) -> -39177 | H95: =IFERROR('Cash Flow Data'!J25,0) -> -26360 | I95: =IFERROR('Cash Flow Data'!K25,0) -> -10226 | J95: =IFERROR('Cash Flow Data'!L25,0) -> -11908 | ... L95: =IFERROR('Cash Flow Data'!N25,0) -> -23916
B96: Interest paid fin | C96: =IFERROR('Cash Flow Data'!E26,0) -> -4733 | D96: =IFERROR('Cash Flow Data'!F26,0) -> -5146 | E96: =IFERROR('Cash Flow Data'!G26,0) -> -6901 | F96: =IFERROR('Cash Flow Data'!H26,0) -> -7419 | G96: =IFERROR('Cash Flow Data'!I26,0) -> -6804 | H96: =IFERROR('Cash Flow Data'!J26,0) -> -4687 | I96: =IFERROR('Cash Flow Data'!K26,0) -> -6120 | J96: =IFERROR('Cash Flow Data'!L26,0) -> -8145 | ... L96: =IFERROR('Cash Flow Data'!N26,0) -> -8066
B97: Dividends paid | C97: =IFERROR('Cash Flow Data'!E27,0) -> -791 | D97: =IFERROR('Cash Flow Data'!F27,0) -> -982 | E97: =IFERROR('Cash Flow Data'!G27,0) -> -1186 | F97: =IFERROR('Cash Flow Data'!H27,0) -> -1507 | G97: =IFERROR('Cash Flow Data'!I27,0) -> -1151 | H97: =IFERROR('Cash Flow Data'!J27,0) -> -3020 | I97: =IFERROR('Cash Flow Data'!K27,0) -> -6293 | J97: =IFERROR('Cash Flow Data'!L27,0) -> -4429 | ... L97: =IFERROR('Cash Flow Data'!N27,0) -> -4490
B98: Financial liabilities | C98: =IFERROR('Cash Flow Data'!E28,0) -> -208 | D98: =IFERROR('Cash Flow Data'!F28,0) -> -211 | E98: =IFERROR('Cash Flow Data'!G28,0) -> -276 | F98: =IFERROR('Cash Flow Data'!H28,0) -> -1029 | G98: =IFERROR('Cash Flow Data'!I28,0) -> -1284 | H98: =IFERROR('Cash Flow Data'!J28,0) -> -1310 | I98: =IFERROR('Cash Flow Data'!K28,0) -> -1114 | J98: =IFERROR('Cash Flow Data'!L28,0) -> -1140 | ... L98: =IFERROR('Cash Flow Data'!N28,0) -> -1162
B99: Other financing items | C99: =IFERROR('Cash Flow Data'!E29,0) -> 2501 | D99: =IFERROR('Cash Flow Data'!F29,0) -> 3892 | E99: =IFERROR('Cash Flow Data'!G29,0) -> -576 | F99: =IFERROR('Cash Flow Data'!H29,0) -> -564 | G99: =IFERROR('Cash Flow Data'!I29,0) -> -1714 | H99: =IFERROR('Cash Flow Data'!J29,0) -> -789 | I99: =IFERROR('Cash Flow Data'!K29,0) -> 2 | J99: =IFERROR('Cash Flow Data'!L29,0) -> 404 | ... L99: =IFERROR('Cash Flow Data'!N29,0) -> 293
B100: Cash From Financing Activites | C100: =IFERROR(SUM(C93:C99),0) -> -2579 | D100: =IFERROR(SUM(D93:D99),0) -> 6640 | E100: =IFERROR(SUM(E93:E99),0) -> -672 | F100: =IFERROR(SUM(F93:F99),0) -> -1694 | G100: =IFERROR(SUM(G93:G99),0) -> -37090 | H100: =IFERROR(SUM(H93:H99),0) -> -23401 | I100: =IFERROR(SUM(I93:I99),0) -> -6981 | J100: =IFERROR(SUM(J93:J99),0) -> -11098 | ... L100: =IFERROR(SUM(L93:L99),0) -> -21387
A102: # | B102: Cash Flow Statement
B103: Cash from Operating Activity | C103: =IFERROR('Data Sheet'!B82,0) -> 10824.36 | D103: =IFERROR('Data Sheet'!C82,0) -> 8023.39 | E103: =IFERROR('Data Sheet'!D82,0) -> 25335.95 | F103: =IFERROR('Data Sheet'!E82,0) -> 20168.72 | G103: =IFERROR('Data Sheet'!F82,0) -> 44326.68 | H103: =IFERROR('Data Sheet'!G82,0) -> 44380.99 | I103: =IFERROR('Data Sheet'!H82,0) -> 21683.08 | J103: =IFERROR('Data Sheet'!I82,0) -> 20300.67 | ... L103: =IFERROR('Data Sheet'!K82,0) -> 35064.46
B105: Cash from Investing Activity | C105: =IFERROR('Data Sheet'!B83,0) -> -9489.65 | D105: =IFERROR('Data Sheet'!C83,0) -> -11730.31 | E105: =IFERROR('Data Sheet'!D83,0) -> -29176.45 | F105: =IFERROR('Data Sheet'!E83,0) -> -14012.06 | G105: =IFERROR('Data Sheet'!F83,0) -> -9437.27 | H105: =IFERROR('Data Sheet'!G83,0) -> -10905.02 | I105: =IFERROR('Data Sheet'!H83,0) -> -18179.45 | J105: =IFERROR('Data Sheet'!I83,0) -> -14252.74 | ... L105: =IFERROR('Data Sheet'!K83,0) -> -14397.35
B107: Cash from Financing Activity | C107: =IFERROR('Data Sheet'!B84,0) -> -2579.36 | D107: =IFERROR('Data Sheet'!C84,0) -> 6639.94 | E107: =IFERROR('Data Sheet'!D84,0) -> -672.7 | F107: =IFERROR('Data Sheet'!E84,0) -> -1694.62 | G107: =IFERROR('Data Sheet'!F84,0) -> -37089.67 | H107: =IFERROR('Data Sheet'!G84,0) -> -23401.09 | I107: =IFERROR('Data Sheet'!H84,0) -> -6980.69 | J107: =IFERROR('Data Sheet'!I84,0) -> -11096.99 | ... L107: =IFERROR('Data Sheet'!K84,0) -> -21387.12
B109: Net Cash Flow | C109: =IFERROR(SUM(C103,C105,C107),0) -> -1244.65 | D109: =IFERROR(SUM(D103,D105,D107),0) -> 2933.02 | E109: =IFERROR(SUM(E103,E105,E107),0) -> -4513.2 | F109: =IFERROR(SUM(F103,F105,F107),0) -> 4462.04 | G109: =IFERROR(SUM(G103,G105,G107),0) -> -2200.26 | H109: =IFERROR(SUM(H103,H105,H107),0) -> 10074.88 | I109: =IFERROR(SUM(I103,I105,I107),0) -> -3477.06 | J109: =IFERROR(SUM(J103,J105,J107),0) -> -5049.06 | ... L109: =IFERROR(SUM(L103,L105,L107),0) -> -720.01

Sheet Ratio Analysis
B2: ="Ratio Analysis of - "&'Data Sheet'!B1 -> Ratio Analysis of - TATA STEEL LTD
A3: # | B3: Years | C3: ='Data Sheet'!B16 -> 42825 | D3: ='Data Sheet'!C16 -> 43190 | E3: ='Data Sheet'!D16 -> 43555 | F3: ='Data Sheet'!E16 -> 43921 | G3: ='Data Sheet'!F16 -> 44286 | H3: ='Data Sheet'!G16 -> 44651 | I3: ='Data Sheet'!H16 -> 45016 | J3: ='Data Sheet'!I16 -> 45382 | ... L3: ='Data Sheet'!K16 -> 46112 | M3: Trend | N3: Mean | O3: Median
B5: Sales Growth | D5: =IFERROR('HistoricalFS '!D6,0) -> 0.097504065 | E5: =IFERROR('HistoricalFS '!E6,0) -> 0.27927124 | F5: =IFERROR('HistoricalFS '!F6,0) -> -0.1132267 | G5: =IFERROR('HistoricalFS '!G6,0) -> 0.11916142 | H5: =IFERROR('HistoricalFS '!H6,0) -> 0.55906968 | I5: =IFERROR('HistoricalFS '!I6,0) -> -0.0024859898 | J5: =IFERROR('HistoricalFS '!J6,0) -> -0.058277186 | K5: =IFERROR('HistoricalFS '!K6,0) -> -0.046377073 | L5: =IFERROR('HistoricalFS '!L6,0) -> 0.062218696 | N5: =IFERROR(AVERAGE(D5:L5),0) -> 0.099650904 | O5: =IFERROR(MEDIAN(D5:L5),0) -> 0.062218696
B6: EBITDA Growth | D6: =IFERROR('HistoricalFS '!D17/'HistoricalFS '!C17-1,0) -> 0.6306903 | E6: =IFERROR('HistoricalFS '!E17/'HistoricalFS '!D17-1,0) -> 0.36788877 | F6: =IFERROR('HistoricalFS '!F17/'HistoricalFS '!E17-1,0) -> -0.40436152 | G6: =IFERROR('HistoricalFS '!G17/'HistoricalFS '!F17-1,0) -> 0.74678779 | H6: =IFERROR('HistoricalFS '!H17/'HistoricalFS '!G17-1,0) -> 1.081347 | I6: =IFERROR('HistoricalFS '!I17/'HistoricalFS '!H17-1,0) -> -0.49125555 | J6: =IFERROR('HistoricalFS '!J17/'HistoricalFS '!I17-1,0) -> -0.31121332 | K6: =IFERROR('HistoricalFS '!K17/'HistoricalFS '!J17-1,0) -> 0.13711529 | L6: =IFERROR('HistoricalFS '!L17/'HistoricalFS '!K17-1,0) -> 0.35788714 | N6: =IFERROR(AVERAGE(D6:L6),0) -> 0.23498732 | O6: =IFERROR(MEDIAN(D6:L6),0) -> 0.35788714
B7: EBIT Growth | D7: =IFERROR('HistoricalFS '!D26/'HistoricalFS '!C26-1,0) -> 3.267891 | E7: =IFERROR('HistoricalFS '!E26/'HistoricalFS '!D26-1,0) -> 0.39851906 | F7: =IFERROR('HistoricalFS '!F26/'HistoricalFS '!E26-1,0) -> -0.89600169 | G7: =IFERROR('HistoricalFS '!G26/'HistoricalFS '!F26-1,0) -> 8.1773694 | H7: =IFERROR('HistoricalFS '!H26/'HistoricalFS '!G26-1,0) -> 2.5807379 | I7: =IFERROR('HistoricalFS '!I26/'HistoricalFS '!H26-1,0) -> -0.65936393 | J7: =IFERROR('HistoricalFS '!J26/'HistoricalFS '!I26-1,0) -> -0.70850149 | K7: =IFERROR('HistoricalFS '!K26/'HistoricalFS '!J26-1,0) -> 0.55122998 | L7: =IFERROR('HistoricalFS '!L26/'HistoricalFS '!K26-1,0) -> 1.0210359 | N7: =IFERROR(AVERAGE(D7:L7),0) -> 1.5258796 | O7: =IFERROR(MEDIAN(D7:L7),0) -> 0.55122998
B8: Net Profit Growth | D8: =IFERROR('HistoricalFS '!D32/-'HistoricalFS '!C32-1,0) -> 17.037263 | E8: =IFERROR('HistoricalFS '!E32/'HistoricalFS '!D32-1,0) -> 0.11008091 | F8: =IFERROR('HistoricalFS '!F32/'HistoricalFS '!E32-1,0) -> -0.465997 | G8: =IFERROR('HistoricalFS '!G32/'HistoricalFS '!F32-1,0) -> 0.9742315 | H8: =IFERROR('HistoricalFS '!H32/'HistoricalFS '!G32-1,0) -> 4.0498476 | I8: =IFERROR('HistoricalFS '!I32/'HistoricalFS '!H32-1,0) -> -0.83914468 | J8: =IFERROR('HistoricalFS '!J32/'HistoricalFS '!I32-1,0) -> -0.83161121 | K8: =IFERROR('HistoricalFS '!K32/'HistoricalFS '!J32-1,0) -> 1.0966028 | L8: =IFERROR('HistoricalFS '!L32/'HistoricalFS '!K32-1,0) -> 3.4177826 | N8: =IFERROR(AVERAGE(D8:L8),0) -> 2.7276729 | O8: =IFERROR(MEDIAN(D8:L8),0) -> 0.9742315
B9: Dividend Growth | D9: =IFERROR('HistoricalFS '!D40/'HistoricalFS '!C40-1,0) -> 0.18021551 | E9: =IFERROR('HistoricalFS '!E40/'HistoricalFS '!D40-1,0) -> 0.29997536 | F9: =IFERROR('HistoricalFS '!F40/'HistoricalFS '!E40-1,0) -> -0.23076148 | G9: =IFERROR('HistoricalFS '!G40/'HistoricalFS '!F40-1,0) -> 1.4617851 | H9: =IFERROR('HistoricalFS '!H40/'HistoricalFS '!G40-1,0) -> 1.0381154 | I9: =IFERROR('HistoricalFS '!I40/'HistoricalFS '!H40-1,0) -> -0.29459179 | J9: =IFERROR('HistoricalFS '!J40/'HistoricalFS '!I40-1,0) -> 1.5657977e-05 | K9: =IFERROR('HistoricalFS '!K40/'HistoricalFS '!J40-1,0) -> 0 | L9: =IFERROR('HistoricalFS '!L40/'HistoricalFS '!K40-1,0) -> 0.1111121 | N9: =IFERROR(AVERAGE(D9:L9),0) -> 0.28509621 | O9: =IFERROR(MEDIAN(D9:L9),0) -> 0.1111121
B11: Gross Margin | C11: =IFERROR('HistoricalFS '!C12,0) -> 0.30919421 | D11: =IFERROR('HistoricalFS '!D12,0) -> 0.31269218 | E11: =IFERROR('HistoricalFS '!E12,0) -> 0.33030553 | F11: =IFERROR('HistoricalFS '!F12,0) -> 0.26646118 | G11: =IFERROR('HistoricalFS '!G12,0) -> 0.34188745 | H11: =IFERROR('HistoricalFS '!H12,0) -> 0.41135564 | I11: =IFERROR('HistoricalFS '!I12,0) -> 0.26719791 | J11: =IFERROR('HistoricalFS '!J12,0) -> 0.20079323 | ... L11: =IFERROR('HistoricalFS '!L12,0) -> 0.26149813 | N11: =IFERROR(AVERAGE(C11:L11),0) -> 0.29156574 | O11: =IFERROR(MEDIAN(C11:L11),0) -> 0.28819606
B12: EBITDA Margin | C12: =IFERROR('HistoricalFS '!C18,0) -> 0.11704094 | D12: =IFERROR('HistoricalFS '!D18,0) -> 0.17390143 | E12: =IFERROR('HistoricalFS '!E18,0) -> 0.18594792 | F12: =IFERROR('HistoricalFS '!F18,0) -> 0.12489972 | G12: =IFERROR('HistoricalFS '!G18,0) -> 0.19494355 | H12: =IFERROR('HistoricalFS '!H18,0) -> 0.26024826 | I12: =IFERROR('HistoricalFS '!I18,0) -> 0.13272983 | J12: =IFERROR('HistoricalFS '!J18,0) -> 0.09708009 | ... L12: =IFERROR('HistoricalFS '!L18,0) -> 0.1479816 | N12: =IFERROR(AVERAGE(C12:L12),0) -> 0.15505332 | O12: =IFERROR(MEDIAN(C12:L12),0) -> 0.14035571
B13: EBIT Margin | C13: =IFERROR(('HistoricalFS '!C17-'HistoricalFS '!C23)/'HistoricalFS '!C5,0) -> 0.066525277 | D13: =IFERROR(('HistoricalFS '!D17-'HistoricalFS '!D23)/'HistoricalFS '!D5,0) -> 0.12731528 | E13: =IFERROR(('HistoricalFS '!E17-'HistoricalFS '!E23)/'HistoricalFS '!E5,0) -> 0.13938308 | F13: =IFERROR(('HistoricalFS '!F17-'HistoricalFS '!F23)/'HistoricalFS '!F5,0) -> 0.064529725 | G13: =IFERROR(('HistoricalFS '!G17-'HistoricalFS '!G23)/'HistoricalFS '!G5,0) -> 0.13593413 | H13: =IFERROR(('HistoricalFS '!H17-'HistoricalFS '!H23)/'HistoricalFS '!H5,0) -> 0.22294337 | I13: =IFERROR(('HistoricalFS '!I17-'HistoricalFS '!I23)/'HistoricalFS '!I5,0) -> 0.094369041 | J13: =IFERROR(('HistoricalFS '!J17-'HistoricalFS '!J23)/'HistoricalFS '!J5,0) -> 0.053958711 | ... L13: =IFERROR(('HistoricalFS '!L17-'HistoricalFS '!L23)/'HistoricalFS '!L5,0) -> 0.096484603 | N13: =IFERROR(AVERAGE(C13:L13),0) -> 0.10695175 | O13: =IFERROR(MEDIAN(C13:L13),0) -> 0.095426822
B14: EBT Margin | C14: =IFERROR('HistoricalFS '!C27,0) -> 0.021358525 | D14: =IFERROR('HistoricalFS '!D27,0) -> 0.083057422 | E14: =IFERROR('HistoricalFS '!E27,0) -> 0.090799656 | F14: =IFERROR('HistoricalFS '!F27,0) -> 0.010648732 | G14: =IFERROR('HistoricalFS '!G27,0) -> 0.087321939 | H14: =IFERROR('HistoricalFS '!H27,0) -> 0.20055356 | I14: =IFERROR('HistoricalFS '!I27,0) -> 0.068486032 | J14: =IFERROR('HistoricalFS '!J27,0) -> 0.021198994 | ... L14: =IFERROR('HistoricalFS '!L27,0) -> 0.065610726 | N14: =IFERROR(AVERAGE(C14:L14),0) -> 0.068351936 | O14: =IFERROR(MEDIAN(C14:L14),0) -> 0.067048379
B15: Net Profit Margin | C15: =IFERROR('HistoricalFS '!C33,0) -> -0.0033790023 | D15: =IFERROR('HistoricalFS '!D33,0) -> 0.055533239 | E15: =IFERROR('HistoricalFS '!E33,0) -> 0.048188677 | F15: =IFERROR('HistoricalFS '!F33,0) -> 0.029018575 | G15: =IFERROR('HistoricalFS '!G33,0) -> 0.051189565 | H15: =IFERROR('HistoricalFS '!H33,0) -> 0.16580369 | I15: =IFERROR('HistoricalFS '!I33,0) -> 0.026736873 | J15: =IFERROR('HistoricalFS '!J33,0) -> 0.0047808015 | ... L15: =IFERROR('HistoricalFS '!L33,0) -> 0.043715011 | N15: =IFERROR(AVERAGE(C15:L15),0) -> 0.043209833 | O15: =IFERROR(MEDIAN(C15:L15),0) -> 0.036366793
B17: SalesExpenses%Sale | C17: =IFERROR('HistoricalFS '!C15,0) -> 0.19215326 | D17: =IFERROR('HistoricalFS '!D15,0) -> 0.13879074 | E17: =IFERROR('HistoricalFS '!E15,0) -> 0.14435762 | F17: =IFERROR('HistoricalFS '!F15,0) -> 0.14156147 | G17: =IFERROR('HistoricalFS '!G15,0) -> 0.1469439 | H17: =IFERROR('HistoricalFS '!H15,0) -> 0.15110738 | I17: =IFERROR('HistoricalFS '!I15,0) -> 0.13446808 | J17: =IFERROR('HistoricalFS '!J15,0) -> 0.10371313 | ... L17: =IFERROR('HistoricalFS '!L15,0) -> 0.11351653 | N17: =IFERROR(AVERAGE(C17:L17),0) -> 0.13651242 | O17: =IFERROR(MEDIAN(C17:L17),0) -> 0.1401761
B18: Depreciation%Sale | C18: =IFERROR('HistoricalFS '!C24,0) -> 0.050515666 | D18: =IFERROR('HistoricalFS '!D24,0) -> 0.046586153 | E18: =IFERROR('HistoricalFS '!E24,0) -> 0.046564832 | F18: =IFERROR('HistoricalFS '!F24,0) -> 0.060369992 | G18: =IFERROR('HistoricalFS '!G24,0) -> 0.059009416 | H18: =IFERROR('HistoricalFS '!H24,0) -> 0.03730489 | I18: =IFERROR('HistoricalFS '!I24,0) -> 0.038360784 | J18: =IFERROR('HistoricalFS '!J24,0) -> 0.043121379 | ... L18: =IFERROR('HistoricalFS '!L24,0) -> 0.051496998 | N18: =IFERROR(AVERAGE(C18:L18),0) -> 0.048101571 | O18: =IFERROR(MEDIAN(C18:L18),0) -> 0.047135875
B19: OperatingIncome%Sale | C19: =C13 -> 0.066525277 | D19: =D13 -> 0.12731528 | E19: =E13 -> 0.13938308 | F19: =F13 -> 0.064529725 | G19: =G13 -> 0.13593413 | H19: =H13 -> 0.22294337 | I19: =I13 -> 0.094369041 | J19: =J13 -> 0.053958711 | ... L19: =L13 -> 0.096484603 | N19: =IFERROR(AVERAGE(C19:L19),0) -> 0.10695175 | O19: =IFERROR(MEDIAN(C19:L19),0) -> 0.095426822
B21: Return on Capital Employed | C21: =IFERROR(('HistoricalFS '!C17-'HistoricalFS '!C23)/SUM('HistoricalFS '!C48:C50),0) -> 0.061826653 | D21: =IFERROR(('HistoricalFS '!D17-'HistoricalFS '!D23)/SUM('HistoricalFS '!D48:D50),0) -> 0.10254692 | E21: =IFERROR(('HistoricalFS '!E17-'HistoricalFS '!E23)/SUM('HistoricalFS '!E48:E50),0) -> 0.12946991 | F21: =IFERROR(('HistoricalFS '!F17-'HistoricalFS '!F23)/SUM('HistoricalFS '!F48:F50),0) -> 0.047509827 | G21: =IFERROR(('HistoricalFS '!G17-'HistoricalFS '!G23)/SUM('HistoricalFS '!G48:G50),0) -> 0.13070294 | H21: =IFERROR(('HistoricalFS '!H17-'HistoricalFS '!H23)/SUM('HistoricalFS '!H48:H50),0) -> 0.2862517 | I21: =IFERROR(('HistoricalFS '!I17-'HistoricalFS '!I23)/SUM('HistoricalFS '!I48:I50),0) -> 0.12217019 | J21: =IFERROR(('HistoricalFS '!J17-'HistoricalFS '!J23)/SUM('HistoricalFS '!J48:J50),0) -> 0.069036994 | ... L21: =IFERROR(('HistoricalFS '!L17-'HistoricalFS '!L23)/SUM('HistoricalFS '!L48:L50),0) -> 0.11512725 | N21: =IFERROR(AVERAGE(C21:L21),0) -> 0.11446395 | O21: =IFERROR(MEDIAN(C21:L21),0) -> 0.10883708
B22: Retained Earning % | C22: =IFERROR('HistoricalFS '!C43,0) -> 0 | D22: =IFERROR('HistoricalFS '!D43,0) -> 0.83271775 | E22: =IFERROR('HistoricalFS '!E43,0) -> 0.8041001 | F22: =IFERROR('HistoricalFS '!F43,0) -> 0.71780355 | G22: =IFERROR('HistoricalFS '!G43,0) -> 0.6262152 | H22: =IFERROR('HistoricalFS '!H43,0) -> 0.84602539 | I22: =IFERROR('HistoricalFS '!I43,0) -> 0.3242962 | J22: =IFERROR('HistoricalFS '!J43,0) -> 0 | ... L22: =IFERROR('HistoricalFS '!L43,0) -> 0.50830114 | N22: =IFERROR(AVERAGE(C22:L22),0) -> 0.46594593 | O22: =IFERROR(MEDIAN(C22:L22),0) -> 0.56725817
B23: Return On Equity Share | C23: =IFERROR('HistoricalFS '!C32/SUM('HistoricalFS '!C48:C49),0) -> -0.010033496 | D23: =IFERROR('HistoricalFS '!D32/SUM('HistoricalFS '!D48:D49),0) -> 0.11244209 | E23: =IFERROR('HistoricalFS '!E32/SUM('HistoricalFS '!E48:E49),0) -> 0.1102336 | F23: =IFERROR('HistoricalFS '!F32/SUM('HistoricalFS '!F48:F49),0) -> 0.055143844 | G23: =IFERROR('HistoricalFS '!G32/SUM('HistoricalFS '!G48:G49),0) -> 0.10789524 | H23: =IFERROR('HistoricalFS '!H32/SUM('HistoricalFS '!H48:H49),0) -> 0.35344508 | I23: =IFERROR('HistoricalFS '!I32/SUM('HistoricalFS '!I48:I49),0) -> 0.063119494 | J23: =IFERROR('HistoricalFS '!J32/SUM('HistoricalFS '!J48:J49),0) -> 0.011904286 | ... L23: =IFERROR('HistoricalFS '!L32/SUM('HistoricalFS '!L48:L49),0) -> 0.09932694 | N23: =IFERROR(AVERAGE(C23:L23),0) -> 0.092867276 | O23: =IFERROR(MEDIAN(C23:L23),0) -> 0.081223217
B24: Self Substained Growth rate | C24: =IFERROR(C22*C23,0) -> 0 | D24: =IFERROR(D22*D23,0) -> 0.093632527 | E24: =IFERROR(E22*E23,0) -> 0.088638853 | F24: =IFERROR(F22*F23,0) -> 0.039582447 | G24: =IFERROR(G22*G23,0) -> 0.06756564 | H24: =IFERROR(H22*H23,0) -> 0.29902351 | I24: =IFERROR(I22*I23,0) -> 0.020469412 | J24: =IFERROR(J22*J23,0) -> 0 | ... L24: =IFERROR(L22*L23,0) -> 0.050487997 | N24: =IFERROR(AVERAGE(C24:L24),0) -> 0.065940039 | O24: =IFERROR(MEDIAN(C24:L24),0) -> 0.045035222
B25: Interest Coverage Ratio | C25: =IFERROR(('HistoricalFS '!C17-'HistoricalFS '!C23)/'HistoricalFS '!C20,0) -> 1.4728816 | D25: =IFERROR(('HistoricalFS '!D17-'HistoricalFS '!D23)/'HistoricalFS '!D20,0) -> 2.8766706 | E25: =IFERROR(('HistoricalFS '!E17-'HistoricalFS '!E23)/'HistoricalFS '!E20,0) -> 2.868943 | F25: =IFERROR(('HistoricalFS '!F17-'HistoricalFS '!F23)/'HistoricalFS '!F20,0) -> 1.1976343 | G25: =IFERROR(('HistoricalFS '!G17-'HistoricalFS '!G23)/'HistoricalFS '!G20,0) -> 2.796297 | H25: =IFERROR(('HistoricalFS '!H17-'HistoricalFS '!H23)/'HistoricalFS '!H20,0) -> 9.9573578 | I25: =IFERROR(('HistoricalFS '!I17-'HistoricalFS '!I23)/'HistoricalFS '!I20,0) -> 3.6459841 | J25: =IFERROR(('HistoricalFS '!J17-'HistoricalFS '!J23)/'HistoricalFS '!J20,0) -> 1.6471055 | ... L25: =IFERROR(('HistoricalFS '!L17-'HistoricalFS '!L23)/'HistoricalFS '!L20,0) -> 3.125121 | N25: =IFERROR(AVERAGE(C25:L25),0) -> 3.1614588 | O25: =IFERROR(MEDIAN(C25:L25),0) -> 2.83262
B27: Debtor Turnover Ratio | C27: =IFERROR('HistoricalFS '!C5/'HistoricalFS '!C60,0) -> 9.6919966 | D27: =IFERROR('HistoricalFS '!D5/'HistoricalFS '!D60,0) -> 9.9270163 | E27: =IFERROR('HistoricalFS '!E5/'HistoricalFS '!E60,0) -> 13.349335 | F27: =IFERROR('HistoricalFS '!F5/'HistoricalFS '!F60,0) -> 17.732181 | G27: =IFERROR('HistoricalFS '!G5/'HistoricalFS '!G60,0) -> 16.402518 | H27: =IFERROR('HistoricalFS '!H5/'HistoricalFS '!H60,0) -> 19.92084 | I27: =IFERROR('HistoricalFS '!I5/'HistoricalFS '!I60,0) -> 29.471432 | J27: =IFERROR('HistoricalFS '!J5/'HistoricalFS '!J60,0) -> 36.588119 | ... L27: =IFERROR('HistoricalFS '!L5/'HistoricalFS '!L60,0) -> 47.212758 | N27: =IFERROR(AVERAGE(C27:L27),0) -> 24.184373 | O27: =IFERROR(MEDIAN(C27:L27),0) -> 18.82651
B28: Creditors Turnover Ratio | C28: =IFERROR('HistoricalFS '!C5/'HistoricalFS '!C51,0) -> 2.1757736 | D28: =IFERROR('HistoricalFS '!D5/'HistoricalFS '!D51,0) -> 2.2125526 | E28: =IFERROR('HistoricalFS '!E5/'HistoricalFS '!E51,0) -> 2.5014063 | F28: =IFERROR('HistoricalFS '!F5/'HistoricalFS '!F51,0) -> 2.359989 | G28: =IFERROR('HistoricalFS '!G5/'HistoricalFS '!G51,0) -> 1.9277973 | H28: =IFERROR('HistoricalFS '!H5/'HistoricalFS '!H51,0) -> 2.6397571 | I28: =IFERROR('HistoricalFS '!I5/'HistoricalFS '!I51,0) -> 2.4979585 | J28: =IFERROR('HistoricalFS '!J5/'HistoricalFS '!J51,0) -> 2.5408498 | ... L28: =IFERROR('HistoricalFS '!L5/'HistoricalFS '!L51,0) -> 2.2766565 | N28: =IFERROR(AVERAGE(C28:L28),0) -> 2.3574887 | O28: =IFERROR(MEDIAN(C28:L28),0) -> 2.4010674
B29: Inventory Turnover Ratio | C29: =IFERROR('HistoricalFS '!C5/'HistoricalFS '!C61,0) -> 4.527505 | D29: =IFERROR('HistoricalFS '!D5/'HistoricalFS '!D61,0) -> 4.3503193 | E29: =IFERROR('HistoricalFS '!E5/'HistoricalFS '!E61,0) -> 4.9806827 | F29: =IFERROR('HistoricalFS '!F5/'HistoricalFS '!F61,0) -> 4.5002385 | G29: =IFERROR('HistoricalFS '!G5/'HistoricalFS '!G61,0) -> 4.7023564 | H29: =IFERROR('HistoricalFS '!H5/'HistoricalFS '!H61,0) -> 4.996666 | I29: =IFERROR('HistoricalFS '!I5/'HistoricalFS '!I61,0) -> 4.4721348 | J29: =IFERROR('HistoricalFS '!J5/'HistoricalFS '!J61,0) -> 4.6619688 | ... L29: =IFERROR('HistoricalFS '!L5/'HistoricalFS '!L61,0) -> 4.9130957 | N29: =IFERROR(AVERAGE(C29:L29),0) -> 4.7006129 | O29: =IFERROR(MEDIAN(C29:L29),0) -> 4.6821626
B30: Fixed Assets Turnover Ratio | C30: =IFERROR('HistoricalFS '!C5/'HistoricalFS '!C54,0) -> 1.220559 | D30: =IFERROR('HistoricalFS '!D5/'HistoricalFS '!D54,0) -> 1.2824433 | E30: =IFERROR('HistoricalFS '!E5/'HistoricalFS '!E54,0) -> 1.2670088 | F30: =IFERROR('HistoricalFS '!F5/'HistoricalFS '!F54,0) -> 1.0391376 | G30: =IFERROR('HistoricalFS '!G5/'HistoricalFS '!G54,0) -> 1.1524743 | H30: =IFERROR('HistoricalFS '!H5/'HistoricalFS '!H54,0) -> 1.8303184 | I30: =IFERROR('HistoricalFS '!I5/'HistoricalFS '!I54,0) -> 1.6597345 | J30: =IFERROR('HistoricalFS '!J5/'HistoricalFS '!J54,0) -> 1.5399774 | ... L30: =IFERROR('HistoricalFS '!L5/'HistoricalFS '!L54,0) -> 1.2903249 | N30: =IFERROR(AVERAGE(C30:L30),0) -> 1.3730104 | O30: =IFERROR(MEDIAN(C30:L30),0) -> 1.2863841
B31: Capital Turnover Ratio | C31: =IFERROR('HistoricalFS '!C5/SUM('HistoricalFS '!C48:C49),0) -> 2.9693665 | D31: =IFERROR('HistoricalFS '!D5/SUM('HistoricalFS '!D48:D49),0) -> 2.0247711 | E31: =IFERROR('HistoricalFS '!E5/SUM('HistoricalFS '!E48:E49),0) -> 2.2875416 | F31: =IFERROR('HistoricalFS '!F5/SUM('HistoricalFS '!F48:F49),0) -> 1.9002947 | G31: =IFERROR('HistoricalFS '!G5/SUM('HistoricalFS '!G48:G49),0) -> 2.1077585 | H31: =IFERROR('HistoricalFS '!H5/SUM('HistoricalFS '!H48:H49),0) -> 2.1317082 | I31: =IFERROR('HistoricalFS '!I5/SUM('HistoricalFS '!I48:I49),0) -> 2.3607657 | J31: =IFERROR('HistoricalFS '!J5/SUM('HistoricalFS '!J48:J49),0) -> 2.4900189 | ... L31: =IFERROR('HistoricalFS '!L5/SUM('HistoricalFS '!L48:L49),0) -> 2.2721472 | N31: =IFERROR(AVERAGE(C31:L31),0) -> 2.294147 | O31: =IFERROR(MEDIAN(C31:L31),0) -> 2.2798444
B33: Debtors days | C33: =IFERROR(365/C27,0) -> 37.659939 | D33: =IFERROR(365/D27,0) -> 36.768349 | E33: =IFERROR(365/E27,0) -> 27.342187 | F33: =IFERROR(365/F27,0) -> 20.584045 | G33: =IFERROR(365/G27,0) -> 22.252681 | H33: =IFERROR(365/H27,0) -> 18.322521 | I33: =IFERROR(365/I27,0) -> 12.384875 | J33: =IFERROR(365/J27,0) -> 9.975916 | ... L33: =IFERROR(365/L27,0) -> 7.7309611 | N33: =IFERROR(AVERAGE(C33:L33),0) -> 20.180659 | O33: =IFERROR(MEDIAN(C33:L33),0) -> 19.453283
B34: Payable days | C34: =IFERROR(365/C28,0) -> 167.75643 | D34: =IFERROR(365/D28,0) -> 164.96783 | E34: =IFERROR(365/E28,0) -> 145.91792 | F34: =IFERROR(365/F28,0) -> 154.66174 | G34: =IFERROR(365/G28,0) -> 189.33526 | H34: =IFERROR(365/H28,0) -> 138.2703 | I34: =IFERROR(365/I28,0) -> 146.11932 | J34: =IFERROR(365/J28,0) -> 143.65273 | ... L34: =IFERROR(365/L28,0) -> 160.32282 | N34: =IFERROR(AVERAGE(C34:L34),0) -> 156.04631 | O34: =IFERROR(MEDIAN(C34:L34),0) -> 152.06023
B35: Inventory days | C35: =IFERROR(365/C29,0) -> 80.618353 | D35: =IFERROR(365/D29,0) -> 83.901887 | E35: =IFERROR(365/E29,0) -> 73.283126 | F35: =IFERROR(365/F29,0) -> 81.106812 | G35: =IFERROR(365/G29,0) -> 77.620658 | H35: =IFERROR(365/H29,0) -> 73.048709 | I35: =IFERROR(365/I29,0) -> 81.616503 | J35: =IFERROR(365/J29,0) -> 78.293102 | ... L35: =IFERROR(365/L29,0) -> 74.291246 | N35: =IFERROR(AVERAGE(C35:L35),0) -> 77.825253 | O35: =IFERROR(MEDIAN(C35:L35),0) -> 77.95688
B36: Cash Conversion Cycle (in days) | C36: =IFERROR(SUM(C33,C35)-C34,0) -> -49.478134 | D36: =IFERROR(SUM(D33,D35)-D34,0) -> -44.297593 | E36: =IFERROR(SUM(E33,E35)-E34,0) -> -45.292607 | F36: =IFERROR(SUM(F33,F35)-F34,0) -> -52.970883 | G36: =IFERROR(SUM(G33,G35)-G34,0) -> -89.461918 | H36: =IFERROR(SUM(H33,H35)-H34,0) -> -46.899069 | I36: =IFERROR(SUM(I33,I35)-I34,0) -> -52.117944 | J36: =IFERROR(SUM(J33,J35)-J34,0) -> -55.383708 | ... L36: =IFERROR(SUM(L33,L35)-L34,0) -> -78.300618 | N36: =IFERROR(AVERAGE(C36:L36),0) -> -58.040393 | O36: =IFERROR(MEDIAN(C36:L36),0) -> -52.544413
B38: CFO/Sales | C38: =IFERROR('HistoricalFS '!C103/'HistoricalFS '!C5,0) -> 0.096388387 | D38: =IFERROR('HistoricalFS '!D103/'HistoricalFS '!D5,0) -> 0.06509899 | E38: =IFERROR('HistoricalFS '!E103/'HistoricalFS '!E5,0) -> 0.16069076 | F38: =IFERROR('HistoricalFS '!F103/'HistoricalFS '!F5,0) -> 0.1442512 | G38: =IFERROR('HistoricalFS '!G103/'HistoricalFS '!G5,0) -> 0.28327848 | H38: =IFERROR('HistoricalFS '!H103/'HistoricalFS '!H5,0) -> 0.18191975 | I38: =IFERROR('HistoricalFS '!I103/'HistoricalFS '!I5,0) -> 0.08910146 | J38: =IFERROR('HistoricalFS '!J103/'HistoricalFS '!J5,0) -> 0.088583152 | ... L38: =IFERROR('HistoricalFS '!L103/'HistoricalFS '!L5,0) -> 0.1510488 | N38: =IFERROR(AVERAGE(C38:L38),0) -> 0.13662332 | O38: =IFERROR(MEDIAN(C38:L38),0) -> 0.12506171
B39: CFO/Total Assets | C39: =IFERROR('HistoricalFS '!C103/'HistoricalFS '!C65,0) -> 0.062769064 | D39: =IFERROR('HistoricalFS '!D103/'HistoricalFS '!D65,0) -> 0.038440532 | E39: =IFERROR('HistoricalFS '!E103/'HistoricalFS '!E65,0) -> 0.10884382 | F39: =IFERROR('HistoricalFS '!F103/'HistoricalFS '!F65,0) -> 0.080950396 | G39: =IFERROR('HistoricalFS '!G103/'HistoricalFS '!G65,0) -> 0.18173436 | H39: =IFERROR('HistoricalFS '!H103/'HistoricalFS '!H65,0) -> 0.15714442 | I39: =IFERROR('HistoricalFS '!I103/'HistoricalFS '!I65,0) -> 0.075975475 | J39: =IFERROR('HistoricalFS '!J103/'HistoricalFS '!J65,0) -> 0.075379628 | ... L39: =IFERROR('HistoricalFS '!L103/'HistoricalFS '!L65,0) -> 0.11825542 | N39: =IFERROR(AVERAGE(C39:L39),0) -> 0.098348969 | O39: =IFERROR(MEDIAN(C39:L39),0) -> 0.082473491
B40: CFO/Total Debt | C40: =IFERROR('HistoricalFS '!C103/'HistoricalFS '!C50,0) -> 0.13039121 | D40: =IFERROR('HistoricalFS '!D103/'HistoricalFS '!D50,0) -> 0.087071588 | E40: =IFERROR('HistoricalFS '!E103/'HistoricalFS '!E50,0) -> 0.25130827 | F40: =IFERROR('HistoricalFS '!F103/'HistoricalFS '!F50,0) -> 0.17337774 | G40: =IFERROR('HistoricalFS '!G103/'HistoricalFS '!G50,0) -> 0.50085846 | H40: =IFERROR('HistoricalFS '!H103/'HistoricalFS '!H50,0) -> 0.58735041 | I40: =IFERROR('HistoricalFS '!I103/'HistoricalFS '!I50,0) -> 0.25541643 | J40: =IFERROR('HistoricalFS '!J103/'HistoricalFS '!J50,0) -> 0.23312099 | ... L40: =IFERROR('HistoricalFS '!L103/'HistoricalFS '!L50,0) -> 0.37956075 | N40: =IFERROR(AVERAGE(C40:L40),0) -> 0.28425205 | O40: =IFERROR(MEDIAN(C40:L40),0) -> 0.24768643

Sheet Forecasting
B2: ='Data Sheet'!B1&" -"&'Data Sheet'!A17 &" Forecasting" -> TATA STEEL LTD -Sales Forecasting | G2: ='Data Sheet'!B1&" - "&'HistoricalFS '!B17 &" Forecasting" -> TATA STEEL LTD - EBITDA Forecasting | L2: ='Data Sheet'!B1&" - "&'HistoricalFS '!B37 &" Forecasting" -> TATA STEEL LTD - Earning Per Share Forecasting
B3: Growth Year | C3: Year | D3: Sales | E3: Sales Growth | G3: Growth Year | H3: Year | I3: Sales | J3: Sales Growth | L3: Growth Year | M3: Year | N3: Sales | O3: Sales Growth | Q3: SUMMARY OUTPUT
B4: 1 | C4: ='Data Sheet'!$B$16 -> 42825 | D4: {=TRANSPOSE('Data Sheet'!B17:K17)} -> 112299.42 | G4: 1 | H4: ='Data Sheet'!$B$16 -> 42825 | I4: {=TRANSPOSE('HistoricalFS '!C17:M17)} -> 13143.63 | L4: 1 | M4: ='Data Sheet'!$B$16 -> 42825 | N4: {=TRANSPOSE('HistoricalFS '!C37:M37)} -> -0.33681277
B5: =B4+1 -> 2 | C5: =C4+365 -> 43190 | D5: 123249.07 | E5: =D5/D4-1 -> 0.097504065 | G5: =G4+1 -> 2 | H5: =H4+365 -> 43190 | I5: 21433.19 | J5: =I5/I4-1 -> 0.6306903 | L5: =L4+1 -> 2 | M5: =M4+365 -> 43190 | N5: 6.0759357 | O5: =N5/N4-1 -> -19.039505 | Q5: Regression Statistics
B6: =B5+1 -> 3 | C6: =C5+365 -> 43555 | D6: 157668.99 | E6: =D6/D5-1 -> 0.27927124 | G6: =G5+1 -> 3 | H6: =H5+365 -> 43555 | I6: 29318.22 | J6: =I6/I5-1 -> 0.36788877 | L6: =L5+1 -> 3 | M6: =M5+365 -> 43555 | N6: 6.7447203 | O6: =N6/N5-1 -> 0.11007106 | Q6: Multiple R | R6: 0.87298507
B7: =B6+1 -> 4 | C7: =C6+365 -> 43920 | D7: 139816.65 | E7: =D7/D6-1 -> -0.1132267 | G7: =G6+1 -> 4 | H7: =H6+365 -> 43920 | I7: 17463.06 | J7: =I7/I6-1 -> -0.40436152 | L7: =L6+1 -> 4 | M7: =M6+365 -> 43920 | N7: 3.6017009 | O7: =N7/N6-1 -> -0.465997 | Q7: R Square | R7: 0.76210294
B8: =B7+1 -> 5 | C8: =C7+365 -> 44285 | D8: 156477.4 | E8: =D8/D7-1 -> 0.11916142 | G8: =G7+1 -> 5 | H8: =H7+365 -> 44285 | I8: 30504.26 | J8: =I8/I7-1 -> 0.74678779 | L8: =L7+1 -> 5 | M8: =M7+365 -> 44285 | N8: 6.6940305 | O8: =N8/N7-1 -> 0.85857482 | Q8: Adjusted R Square | R8: 0.7323658
B9: =B8+1 -> 6 | C9: =C8+365 -> 44650 | D9: 243959.17 | E9: =D9/D8-1 -> 0.55906968 | G9: =G8+1 -> 6 | H9: =H8+365 -> 44650 | I9: 63489.95 | J9: =I9/I8-1 -> 1.081347 | L9: =L8+1 -> 6 | M9: =M8+365 -> 44650 | N9: 33.119897 | O9: =N9/N8-1 -> 3.9476764 | Q9: Standard Error | R9: 27198.017
B10: =B9+1 -> 7 | C10: =C9+365 -> 45015 | D10: 243352.69 | E10: =D10/D9-1 -> -0.0024859898 | G10: =G9+1 -> 7 | H10: =H9+365 -> 45015 | I10: 32300.16 | J10: =I10/I9-1 -> -0.49125555 | L10: =L9+1 -> 7 | M10: =M9+365 -> 45015 | N10: 5.3238064 | O10: =N10/N9-1 -> -0.83925655 | Q10: Observations | R10: 10
B11: =B10+1 -> 8 | C11: =C10+365 -> 45380 | D11: 229170.78 | E11: =D11/D10-1 -> -0.058277186 | G11: =G10+1 -> 8 | H11: =H10+365 -> 45380 | I11: 22247.92 | J11: =I11/I10-1 -> -0.31121332 | L11: =L10+1 -> 8 | M11: =M10+365 -> 45380 | N11: 0.8776545 | O11: =N11/N10-1 -> -0.8351453
B12: =B11+1 -> 9 | C12: =C11+365 -> 45745 | D12: 218542.51 | E12: =D12/D11-1 -> -0.046377073 | G12: =G11+1 -> 9 | H12: =H11+365 -> 45745 | I12: 25298.45 | J12: =I12/I11-1 -> 0.13711529 | L12: =L11+1 -> 9 | M12: =M11+365 -> 45745 | N12: 1.8400929 | O12: =N12/N11-1 -> 1.0966028 | Q12: ANOVA
B13: =B12+1 -> 10 | C13: =C12+365 -> 46110 | D13: 232139.94 | E13: =D13/D12-1 -> 0.062218696 | G13: =G12+1 -> 10 | H13: =H12+365 -> 46110 | I13: 34352.44 | J13: =I13/I12-1 -> 0.35788714 | L13: =L12+1 -> 10 | M13: =M12+365 -> 46110 | N13: 8.1291305 | O13: =N13/N12-1 -> 3.4177826 | R13: df | S13: SS | T13: MS | U13: F | V13: Significance F
B14: =B13+1 -> 11 | C14: =C13+365 -> 46475 | D14: =FORECAST(B14,$D$4:$D$13,B$4:B$13) -> 269041.58 | E14: =D14/D13-1 -> 0.15896292 | G14: =G13+1 -> 11 | H14: =H13+365 -> 46475 | I14: =FORECAST(G14,$I$4:$I$13,$G$4:$G$13) -> 37624.515 | J14: =I14/I13-1 -> 0.095250138 | L14: =L13+1 -> 11 | M14: =M13+365 -> 46475 | N14: =FORECAST(L14,$N$4:$N$13,$L$4:$L$13) -> 8.8336637 | O14: =N14/N13-1 -> 0.086667725 | Q14: Regression | R14: 1 | S14: 1.8957847e+10 | T14: 1.8957847e+10 | U14: 25.62799 | V14: 0.00097413288
B15: =B14+1 -> 12 | C15: =C14+365 -> 46840 | D15: =FORECAST(B15,$D$4:$D$13,B$4:B$13) -> 284200.48 | E15: =D15/D14-1 -> 0.056344058 | G15: =G14+1 -> 12 | H15: =H14+365 -> 46840 | I15: =FORECAST(G15,$I$4:$I$13,$G$4:$G$13) -> 39200.767 | J15: =I15/I14-1 -> 0.041894284 | L15: =L14+1 -> 12 | M15: =M14+365 -> 46840 | N15: =FORECAST(L15,$N$4:$N$13,$L$4:$L$13) -> 9.1294179 | O15: =N15/N14-1 -> 0.033480356 | Q15: Residual | R15: 8 | S15: 5.9178569e+09 | T15: 7.3973211e+08
B16: =B15+1 -> 13 | C16: =C15+365 -> 47205 | D16: =FORECAST(B16,$D$4:$D$13,B$4:B$13) -> 299359.37 | E16: =D16/D15-1 -> 0.053338737 | G16: =G15+1 -> 13 | H16: =H15+365 -> 47205 | I16: =FORECAST(G16,$I$4:$I$13,$G$4:$G$13) -> 40777.019 | J16: =I16/I15-1 -> 0.040209727 | L16: =L15+1 -> 13 | M16: =M15+365 -> 47205 | N16: =FORECAST(L16,$N$4:$N$13,$L$4:$L$13) -> 9.4251721 | O16: =N16/N15-1 -> 0.032395735 | Q16: Total | R16: 9 | S16: 2.4875704e+10
B17: =B16+1 -> 14 | C17: =C16+365 -> 47570 | D17: =FORECAST(B17,$D$4:$D$13,B$4:B$13) -> 314518.27 | E17: =D17/D16-1 -> 0.050637782 | G17: =G16+1 -> 14 | H17: =H16+365 -> 47570 | I17: =FORECAST(G17,$I$4:$I$13,$G$4:$G$13) -> 42353.271 | J17: =I17/I16-1 -> 0.038655404 | L17: =L16+1 -> 14 | M17: =M16+365 -> 47570 | N17: =FORECAST(L17,$N$4:$N$13,$L$4:$L$13) -> 9.7209263 | O17: =N17/N16-1 -> 0.031379183
R18: Coefficients | S18: Standard Error | T18: t Stat | U18: P-value | V18: Lower 95% | W18: Upper 95% | X18: Lower 95.0% | Y18: Upper 95.0%
Q19: Intercept | R19: 102293.74 | S19: 18579.782 | T19: 5.505648 | U19: 0.00056993577 | V19: 59448.687 | W19: 145138.8 | X19: 59448.687 | Y19: 145138.8
Q20: Growth Year | R20: 15158.895 | S20: 2994.4031 | T20: 5.0624095 | U20: 0.00097413288 | V20: 8253.7887 | W20: 22064 | X20: 8253.7887 | Y20: 22064
S26: 204737

Sheet Cash Flow Data
C2: 42064 | D2: 42430 | E2: 42795 | F2: 43160 | G2: 43525 | H2: 43891 | I2: 44256 | J2: 44621 | K2: 44986 | L2: 45352 | M2: 45717 | N2: 46082
B3: Cash from Operating Activity - | C3: 11880 | D3: 11455 | E3: 10824 | F3: 8023 | G3: 25336 | H3: 20169 | I3: 44327 | J3: 44381 | K3: 21683 | L3: 20301 | M3: 23138 | N3: 35064
B4: Profit from operations | C4: 13955 | D4: 6824 | E4: 17581 | F4: 20187 | G4: 27840 | H4: 18078 | I4: 28540 | J4: 65900 | K4: 30908 | L4: 22237 | M4: 23929 | N4: 34219
B5: Receivables | C5: 1442 | D5: 0 | E5: 0 | F5: 0 | G5: 0 | H5: 0 | I5: 0 | J5: 0 | K5: 0 | L5: 0 | M5: 0 | N5: 0
B6: Inventory | C6: -485 | D6: 5618 | E6: -8243 | F6: -1595 | G6: -1069 | H6: 1562 | I6: 46 | J6: -16917 | K6: -4031 | L6: 5566 | M6: 4776 | N6: 1290
B7: Payables | C7: -605 | D7: 0 | E7: 0 | F7: 0 | G7: 0 | H7: 0 | I7: 0 | J7: 0 | K7: 0 | L7: 0 | M7: 0 | N7: 0
B8: Other WC items | C8: 0 | D8: 548 | E8: 3329 | F8: -7680 | G8: 3659 | H8: 2634 | I8: 16446 | J8: 7299 | K8: 325 | L8: -2182 | M8: -2569 | N8: 4152
B9: Working capital changes | C9: 351 | D9: 6166 | E9: -4914 | F9: -9276 | G9: 2591 | H9: 4196 | I9: 16491 | J9: -9618 | K9: -3706 | L9: 3384 | M9: 2207 | N9: 5442
B10: Direct taxes | C10: -2427 | D10: -1534 | E10: -1843 | F10: -2888 | G10: -5094 | H10: -2106 | I10: -704 | J10: -11902 | K10: -5519 | L10: -5320 | M10: -2998 | N10: -4597
B11: Cash from Investing Activity - | C11: -9021 | D11: -8794 | E11: -9490 | F11: -11730 | G11: -29176 | H11: -14012 | I11: -9437 | J11: -10905 | K11: -18179 | L11: -14253 | M11: -13611 | N11: -14397
B12: Fixed assets purchased | C12: -13492 | D12: -10163 | E12: -7716 | F12: -7478 | G12: -9091 | H12: -10398 | I12: -6979 | J12: -10522 | K12: -14142 | L12: -18207 | M12: -15671 | N12: -14559
B13: Fixed assets sold | C13: 1444 | D13: 231 | E13: 289 | F13: 179 | G13: 467 | H13: 386 | I13: 445 | J13: 569 | K13: 328 | L13: 475 | M13: 1264 | N13: 1401
B14: Investments purchased | C14: 1531 | D14: -3796 | E14: -861 | F14: -8641 | G14: -490 | H14: -828 | I14: -3631 | J14: -1153 | K14: -326 | L14: -4 | M14: -393 | N14: -553
... B30: Net Cash Flow | C30: 241 | D30: -2068 | E30: -1245 | F30: 2933 | G30: -4513 | H30: 4462 | I30: -2200 | J30: 10075 | K30: -3477 | L30: -5049 | M30: 2524 | N30: -720

Sheet WACC
B2: Weighted average cost of captial
B3: Tata Steel LTd - WACC Calculation
A5: # | B5: Peer comps
G6: Debt/ | H6: Debt/ | I6: Levered | J6: Unleverd | S6: Debt/ | T6: Debt/
B7: Name of the company | C7: Country | D7: Debt | E7: Equity | F7: Tax rate 1 | G7: Equity | H7: Capital | I7: Beta 2 | J7: Beta 3 | N7: Name of the company | O7: Country | P7: Debt | Q7: Equity | R7: Tax rate 1 | S7: Equity | T7: Capital
B9: JSW Steel | C9: India | D9: 99310 | E9: 324022.65 | F9: 0.3 | G9: =D9/E9 -> 0.30649092 | H9: =D9/(E9+D9) -> 0.23459093 | I9: 0.63 | J9: =I9/(1+(1-F9)*G9) -> 0.51871335 | N9: Tata Steel | O9: India | P9: 92381.68 | Q9: 235189.51 | R9: 0.3 | S9: =P9/Q9 -> 0.39279677 | T9: =P9/(Q9+P9) -> 0.28202016
B10: Steel Authority of India | C10: India | D10: 31927.71 | E10: 81288.74 | F10: 0.3 | G10: =D10/E10 -> 0.39276916 | H10: =D10/(E10+D10) -> 0.28200593 | I10: 1.05 | J10: =I10/(1+(1-F10)*G10) -> 0.82356919
B11: Jindal Steel & Power | C11: India | D11: 22609.55 | E11: 118840.26 | F11: 0.3 | G11: =D11/E11 -> 0.1902516 | H11: =D11/(E11+D11) -> 0.1598415 | I11: 0.67 | J11: =I11/(1+(1-F11)*G11) -> 0.59125849
B12: Jindal Stainless | C12: India | D12: 7460.33 | E12: 60829.8 | F12: 0.3 | G12: =D12/E12 -> 0.12264268 | H12: =D12/(E12+D12) -> 0.10924463 | I12: 0.55 | J12: =I12/(1+(1-F12)*G12) -> 0.50651569
E14: Average | F14: =AVERAGE(F9:F12) -> 0.3 | G14: =AVERAGE(G9:G12) -> 0.25303859 | H14: =AVERAGE(H9:H12) -> 0.19642075 | I14: =AVERAGE(I9:I12) -> 0.725 | J14: =AVERAGE(J9:J12) -> 0.61001418
E15: Median | F15: =MEDIAN(F9:F12) -> 0.3 | G15: =MEDIAN(G9:G12) -> 0.24837126 | H15: =MEDIAN(H9:H12) -> 0.19721622 | I15: =MEDIAN(I9:I12) -> 0.65 | J15: =MEDIAN(J9:J12) -> 0.55498592
B18: Cost of debt | G18: Cost of Equity
B20: Pre tax cost of debt | D20: 0.085 | G20: Risk free rate | J20: 0.0689
B21: Tax rate | D21: =R9 -> 0.3 | G21: Equity risk Premium | J21: =RM!G7-WACC!J20 -> 0.083711538
B22: Post tax Cost of debt | D22: =D20*(1-D21) -> 0.0595 | G22: Levered beta 4 | J22: =J31 -> 0.64994547
G23: Cost of Equity | J23: =J20+(J21*J22) -> 0.12330794
G26: Levered beta
B27: Capital Structure
G28: Comps median unlevered beta | J28: =J15 -> 0.55498592
D29: Current | E29: Target | G29: target debt/equity | J29: =E35 -> 0.24443233
B30: Total Debt | C30: =P9 -> 92381.68 | D30: =C30/$C$32 -> 0.28202016 | E30: =H14 -> 0.19642075 | G30: tax rate | J30: =R9 -> 0.3
B31: Total Equity | C31: =Q9 -> 235189.51 | D31: =C31/$C$32 -> 0.71797984 | E31: =E32-E30 -> 0.80357925 | G31: Levered beta | J31: =J28*(1+(1-J30)*J29) -> 0.64994547
B32: Total Capital | C32: =SUM(C30:C31) -> 327571.19 | D32: =C32/$C$32 -> 1 | E32: =D32 -> 1
G34: Weighted Average Cost of capital
B35: Targeted Debt/equity | D35: =D30/D31 -> 0.39279677 | E35: =E30/E31 -> 0.24443233
I36: Total Cost | J36: Total weight
G37: Debt | I37: =D22 -> 0.0595 | J37: =E30 -> 0.19642075
G38: Equity | I38: =J23 -> 0.12330794 | J38: =E31 -> 0.80357925
G39: Total | I39: =SUM(I37:I38) -> 0.18280794 | J39: =SUM(J37:J38) -> 1
G41: WACC | I41: =(I37*J37)+(I38*J38) -> 0.11077473

Sheet Beta
A2: Jindal Steel | F2: Nifty
A5: Month | B5: Closing price | C5: Return | F5: Closing price | G5: Return
A6: 42736 | B6: 78.93 | F6: 8561.3 | J6: Beta | K6: =SLOPE(C62:C121,G62:G121) -> 1.2320132
A7: 42767 | B7: 123.55 | C7: =B7/B6-1 -> 0.56531104 | F7: 8879.6 | G7: =(F7/F6)-1 -> 0.037178933
A8: 42795 | B8: 119.36 | C8: =B8/B7-1 -> -0.033913395 | F8: 9173.7 | G8: =(F8/F7)-1 -> 0.033120861
A9: 42826 | B9: 112.31 | C9: =B9/B8-1 -> -0.059065013 | F9: 9304 | G9: =(F9/F8)-1 -> 0.014203647 | J9: Beta Drafiting
A10: 42856 | B10: 119.71 | C10: =B10/B9-1 -> 0.065889057 | F10: 9621.2 | G10: =(F10/F9)-1 -> 0.034092863
A11: 42887 | B11: 121.38 | C11: =B11/B10-1 -> 0.01395038 | F11: 9520.9 | G11: =(F11/F10)-1 -> -0.010424895 | J11: Levered Raw beta | K11: =K6 -> 1.2320132
A12: 42917 | B12: 150.82 | C12: =B12/B11-1 -> 0.24254408 | F12: 10077 | G12: =(F12/F11)-1 -> 0.058408344 | J12: Raw beta weight | K12: 0.75
A13: 42948 | B13: 135.09 | C13: =B13/B12-1 -> -0.10429651 | F13: 9917.9 | G13: =(F13/F12)-1 -> -0.015788429
A14: 42979 | B14: 133.27 | C14: =B14/B13-1 -> -0.0134725 | F14: 9788.6 | G14: =(F14/F13)-1 -> -0.013037034 | J14: market beta | K14: 1
A15: 43009 | B15: 161.17 | C15: =B15/B14-1 -> 0.20934944 | F15: 10335 | G15: =(F15/F14)-1 -> 0.055820036 | J15: Market Beta weight | K15: 0.25
A16: 43040 | B16: 169.4 | C16: =B16/B15-1 -> 0.051064094 | F16: 10226 | G16: =(F16/F15)-1 -> -0.010546686
A17: 43070 | B17: 202.14 | C17: =B17/B16-1 -> 0.19327037 | F17: 10530 | G17: =(F17/F16)-1 -> 0.029728144 | J17: Adjusted Beta | K17: =(K11*K12)+(K14*K15) -> 1.1740099
A18: 43101 | B18: 261.75 | C18: =B18/B17-1 -> 0.29489463 | F18: 11027.7 | G18: =(F18/F17)-1 -> 0.047264957
A19: 43132 | B19: 250.12 | C19: =B19/B18-1 -> -0.04443171 | F19: 10492.85 | G19: =(F19/F18)-1 -> -0.048500594
A20: 43160 | B20: 214.96 | C20: =B20/B19-1 -> -0.14057253 | F20: 10113.7 | G20: =(F20/F19)-1 -> -0.036134129
A21: 43191 | B21: 248 | C21: =B21/B20-1 -> 0.15370301 | F21: 10739.35 | G21: =(F21/F20)-1 -> 0.061861633
A22: 43221 | B22: 225.76 | C22: =B22/B21-1 -> -0.089677419 | F22: 10736.15 | G22: =(F22/F21)-1 -> -0.00029796962
A23: 43252 | B23: 219.5 | C23: =B23/B22-1 -> -0.027728561 | F23: 10714.3 | G23: =(F23/F22)-1 -> -0.0020351802
A24: 43282 | B24: 201.55 | C24: =B24/B23-1 -> -0.081776765 | F24: 11356.5 | G24: =(F24/F23)-1 -> 0.059938587
A25: 43313 | B25: 216.88 | C25: =B25/B24-1 -> 0.076060531 | F25: 11680.5 | G25: =(F25/F24)-1 -> 0.028529917
A26: 43344 | B26: 193.07 | C26: =B26/B25-1 -> -0.10978421 | F26: 10930.45 | G26: =(F26/F25)-1 -> -0.064213861
A27: 43374 | B27: 167.88 | C27: =B27/B26-1 -> -0.13047081 | F27: 10386.6 | G27: =(F27/F26)-1 -> -0.0497555
A28: 43405 | B28: 152.15 | C28: =B28/B27-1 -> -0.093697879 | F28: 10876.75 | G28: =(F28/F27)-1 -> 0.047190611
A29: 43435 | B29: 162.45 | C29: =B29/B28-1 -> 0.067696352 | F29: 10862.55 | G29: =(F29/F28)-1 -> -0.001305537
... A121: 46235 | B121: 1307 | C121: =B121/B120-1 -> 0.029133858 | F121: 24080 | G121: =(F121/F120)-1 -> -0.012450992
A122: sep | B122: 1302 | C122: =B122/B121-1 -> -0.0038255547 | F122: 23838 | G122: =(F122/F121)-1 -> -0.010049834

Sheet RM
A2: Return on Market
B3: Year | C3: Annual
B4: 2000 | C4: -0.1465 | F4: Average Return | G4: =AVERAGE(C4:C29) -> 0.15261154
B5: 2001 | C5: -0.1394 | F5: Dividend Yield | G5: 2.92% 1
B6: 2002 | C6: 0.0325
B7: 2003 | C7: 0.719 | F7: Total Return on Market | G7: =SUM(G4:G5) -> 0.15261154
B8: 2004 | C8: 0.1068
B9: 2005 | C9: 0.3634
B10: 2006 | C10: 0.3983
B11: 2007 | C11: 0.5477
B12: 2008 | C12: -0.5179
B13: 2009 | C13: 0.7576
B14: 2010 | C14: 0.1795
B15: 2011 | C15: -0.2462
B16: 2012 | C16: 0.277
B17: 2013 | C17: 0.0676
B18: 2014 | C18: 0.3139
B19: 2015 | C19: -0.0406
... B29: 2025 | C29: 0.1051

Sheet Common Size Statement
B2: ="Common Size Income Statement" &" "&"-"&'Data Sheet'!B1 -> Common Size Income Statement -TATA STEEL LTD
B4: Particular | C4: ='Data Sheet'!B16 -> 42825 | D4: ='Data Sheet'!C16 -> 43190 | E4: ='Data Sheet'!D16 -> 43555 | F4: ='Data Sheet'!E16 -> 43921 | G4: ='Data Sheet'!F16 -> 44286 | H4: ='Data Sheet'!G16 -> 44651 | I4: ='Data Sheet'!H16 -> 45016 | J4: ='Data Sheet'!I16 -> 45382 | ... L4: ='Data Sheet'!K16 -> 46112
B6: ='Data Sheet'!A17 -> Sales | C6: ='Data Sheet'!B17/'Data Sheet'!B$17 -> 1 | D6: ='Data Sheet'!C17/'Data Sheet'!C$17 -> 1 | E6: ='Data Sheet'!D17/'Data Sheet'!D$17 -> 1 | F6: ='Data Sheet'!E17/'Data Sheet'!E$17 -> 1 | G6: ='Data Sheet'!F17/'Data Sheet'!F$17 -> 1 | H6: ='Data Sheet'!G17/'Data Sheet'!G$17 -> 1 | I6: ='Data Sheet'!H17/'Data Sheet'!H$17 -> 1 | J6: ='Data Sheet'!I17/'Data Sheet'!I$17 -> 1 | ... L6: ='Data Sheet'!K17/'Data Sheet'!K$17 -> 1
B7: ='Data Sheet'!A18 -> Raw Material Cost | C7: ='Data Sheet'!B18/'Data Sheet'!B$17 -> 0.3904119 | D7: ='Data Sheet'!C18/'Data Sheet'!C$17 -> 0.37433962 | E7: ='Data Sheet'!D18/'Data Sheet'!D$17 -> 0.38610668 | F7: ='Data Sheet'!E18/'Data Sheet'!E$17 -> 0.41511501 | G7: ='Data Sheet'!F18/'Data Sheet'!F$17 -> 0.3521327 | H7: ='Data Sheet'!G18/'Data Sheet'!G$17 -> 0.37332727 | I7: ='Data Sheet'!H18/'Data Sheet'!H$17 -> 0.47912842 | J7: ='Data Sheet'!I18/'Data Sheet'!I$17 -> 0.42547479 | ... L7: ='Data Sheet'!K18/'Data Sheet'!K$17 -> 0.39901824
B8: ='Data Sheet'!A19 -> Change in Inventory | C8: ='Data Sheet'!B19/'Data Sheet'!B$17 -> 0.040410983 | D8: ='Data Sheet'!C19/'Data Sheet'!C$17 -> -0.00080576673 | E8: ='Data Sheet'!D19/'Data Sheet'!D$17 -> 0.00061337363 | F8: ='Data Sheet'!E19/'Data Sheet'!E$17 -> 0.0040427231 | G8: ='Data Sheet'!F19/'Data Sheet'!F$17 -> -0.0096932209 | H8: ='Data Sheet'!G19/'Data Sheet'!G$17 -> 0.031144023 | I8: ='Data Sheet'!H19/'Data Sheet'!H$17 -> 0.01380256 | J8: ='Data Sheet'!I19/'Data Sheet'!I$17 -> -0.019240455 | ... L8: ='Data Sheet'!K19/'Data Sheet'!K$17 -> -0.004263032
B9: ='Data Sheet'!A20 -> Power and Fuel | C9: ='Data Sheet'!B20/'Data Sheet'!B$17 -> 0.046490267 | D9: ='Data Sheet'!C20/'Data Sheet'!C$17 -> 0.036028101 | E9: ='Data Sheet'!D20/'Data Sheet'!D$17 -> 0.033719757 | F9: ='Data Sheet'!E20/'Data Sheet'!E$17 -> 0.03804926 | G9: ='Data Sheet'!F20/'Data Sheet'!F$17 -> 0.036480795 | H9: ='Data Sheet'!G20/'Data Sheet'!G$17 -> 0.032908335 | I9: ='Data Sheet'!H20/'Data Sheet'!H$17 -> 0.039148571 | J9: ='Data Sheet'!I20/'Data Sheet'!I$17 -> 0.072490088 | ... L9: ='Data Sheet'!K20/'Data Sheet'!K$17 -> 0.061743576
B10: ='Data Sheet'!A21 -> Other Mfr. Exp | C10: ='Data Sheet'!B21/'Data Sheet'!B$17 -> 0.14068764 | D10: ='Data Sheet'!C21/'Data Sheet'!C$17 -> 0.13757337 | E10: ='Data Sheet'!D21/'Data Sheet'!D$17 -> 0.13150512 | F10: ='Data Sheet'!E21/'Data Sheet'!E$17 -> 0.15186096 | G10: ='Data Sheet'!F21/'Data Sheet'!F$17 -> 0.13257461 | H10: ='Data Sheet'!G21/'Data Sheet'!G$17 -> 0.11819215 | I10: ='Data Sheet'!H21/'Data Sheet'!H$17 -> 0.1362008 | J10: ='Data Sheet'!I21/'Data Sheet'!I$17 -> 0.17505247 | ... L10: ='Data Sheet'!K21/'Data Sheet'!K$17 -> 0.16148001
B11: ='Data Sheet'!A22 -> Employee Cost | C11: ='Data Sheet'!B22/'Data Sheet'!B$17 -> 0.15362697 | D11: ='Data Sheet'!C22/'Data Sheet'!C$17 -> 0.13856096 | E11: ='Data Sheet'!D22/'Data Sheet'!D$17 -> 0.11897628 | F11: ='Data Sheet'!E22/'Data Sheet'!E$17 -> 0.13255632 | G11: ='Data Sheet'!F22/'Data Sheet'!F$17 -> 0.12723122 | H11: ='Data Sheet'!G22/'Data Sheet'!G$17 -> 0.095360629 | I11: ='Data Sheet'!H22/'Data Sheet'!H$17 -> 0.092126863 | J11: ='Data Sheet'!I22/'Data Sheet'!I$17 -> 0.10694897 | ... L11: ='Data Sheet'!K22/'Data Sheet'!K$17 -> 0.11199701
B12: ='Data Sheet'!A23 -> Selling and admin | C12: ='Data Sheet'!B23/'Data Sheet'!B$17 -> 0.12263928 | D12: ='Data Sheet'!C23/'Data Sheet'!C$17 -> 0.11703025 | E12: ='Data Sheet'!D23/'Data Sheet'!D$17 -> 0.10729529 | F12: ='Data Sheet'!E23/'Data Sheet'!E$17 -> 0.11156804 | G12: ='Data Sheet'!F23/'Data Sheet'!F$17 -> 0.11189967 | H12: ='Data Sheet'!G23/'Data Sheet'!G$17 -> 0.11250108 | I12: ='Data Sheet'!H23/'Data Sheet'!H$17 -> 0.10486804 | J12: ='Data Sheet'!I23/'Data Sheet'!I$17 -> 0.063068992 | ... L12: ='Data Sheet'!K23/'Data Sheet'!K$17 -> 0.057504064
B13: ='Data Sheet'!A24 -> Other Expenses | C13: ='Data Sheet'!B24/'Data Sheet'!B$17 -> 0.069513983 | D13: ='Data Sheet'!C24/'Data Sheet'!C$17 -> 0.021760489 | E13: ='Data Sheet'!D24/'Data Sheet'!D$17 -> 0.037062329 | F13: ='Data Sheet'!E24/'Data Sheet'!E$17 -> 0.029993424 | G13: ='Data Sheet'!F24/'Data Sheet'!F$17 -> 0.03504423 | H13: ='Data Sheet'!G24/'Data Sheet'!G$17 -> 0.038606296 | I13: ='Data Sheet'!H24/'Data Sheet'!H$17 -> 0.029600043 | J13: ='Data Sheet'!I24/'Data Sheet'!I$17 -> 0.040644143 | ... L13: ='Data Sheet'!K24/'Data Sheet'!K$17 -> 0.056012464
B14: ='Data Sheet'!A25 -> Other Income | C14: ='Data Sheet'!B25/'Data Sheet'!B$17 -> -0.033741136 | D14: ='Data Sheet'!C25/'Data Sheet'!C$17 -> 0.0884259 | E14: ='Data Sheet'!D25/'Data Sheet'!D$17 -> 0.0096677857 | F14: ='Data Sheet'!E25/'Data Sheet'!E$17 -> -0.020624368 | G14: ='Data Sheet'!F25/'Data Sheet'!F$17 -> 0.0011489199 | H14: ='Data Sheet'!G25/'Data Sheet'!G$17 -> 0.0053287196 | I14: ='Data Sheet'!H25/'Data Sheet'!H$17 -> 0.006446857 | J14: ='Data Sheet'!I25/'Data Sheet'!I$17 -> -0.02620417 | ... L14: ='Data Sheet'!K25/'Data Sheet'!K$17 -> 0.0031783415
B15: ='Data Sheet'!A26 -> Depreciation | C15: ='Data Sheet'!B26/'Data Sheet'!B$17 -> 0.050515666 | D15: ='Data Sheet'!C26/'Data Sheet'!C$17 -> 0.046586153 | E15: ='Data Sheet'!D26/'Data Sheet'!D$17 -> 0.046564832 | F15: ='Data Sheet'!E26/'Data Sheet'!E$17 -> 0.060369992 | G15: ='Data Sheet'!F26/'Data Sheet'!F$17 -> 0.059009416 | H15: ='Data Sheet'!G26/'Data Sheet'!G$17 -> 0.03730489 | I15: ='Data Sheet'!H26/'Data Sheet'!H$17 -> 0.038360784 | J15: ='Data Sheet'!I26/'Data Sheet'!I$17 -> 0.043121379 | ... L15: ='Data Sheet'!K26/'Data Sheet'!K$17 -> 0.051496998
B16: ='Data Sheet'!A27 -> Interest | C16: ='Data Sheet'!B27/'Data Sheet'!B$17 -> 0.045166752 | D16: ='Data Sheet'!C27/'Data Sheet'!C$17 -> 0.044257859 | E16: ='Data Sheet'!D27/'Data Sheet'!D$17 -> 0.048583428 | F16: ='Data Sheet'!E27/'Data Sheet'!E$17 -> 0.053880993 | G16: ='Data Sheet'!F27/'Data Sheet'!F$17 -> 0.048612196 | H16: ='Data Sheet'!G27/'Data Sheet'!G$17 -> 0.022389812 | I16: ='Data Sheet'!H27/'Data Sheet'!H$17 -> 0.02588301 | J16: ='Data Sheet'!I27/'Data Sheet'!I$17 -> 0.032759717 | ... L16: ='Data Sheet'!K27/'Data Sheet'!K$17 -> 0.030873877
B17: ='Data Sheet'!A28 -> Profit before tax | C17: ='Data Sheet'!B28/'Data Sheet'!B$17 -> -0.012382611 | D17: ='Data Sheet'!C28/'Data Sheet'!C$17 -> 0.17148332 | E17: ='Data Sheet'!D28/'Data Sheet'!D$17 -> 0.10046744 | F17: ='Data Sheet'!E28/'Data Sheet'!E$17 -> -0.0099756359 | G17: ='Data Sheet'!F28/'Data Sheet'!F$17 -> 0.088470859 | H17: ='Data Sheet'!G28/'Data Sheet'!G$17 -> 0.20588228 | I17: ='Data Sheet'!H28/'Data Sheet'!H$17 -> 0.074932889 | J17: ='Data Sheet'!I28/'Data Sheet'!I$17 -> -0.0050051756 | ... L17: ='Data Sheet'!K28/'Data Sheet'!K$17 -> 0.068789067
... B20: ='Data Sheet'!A31 -> Dividend Amount | C20: ='Data Sheet'!B31/'Data Sheet'!B$17 -> 0.0086397597 | D20: ='Data Sheet'!C31/'Data Sheet'!C$17 -> 0.0092897253 | E20: ='Data Sheet'!D31/'Data Sheet'!D$17 -> 0.0094401569 | F20: ='Data Sheet'!E31/'Data Sheet'!E$17 -> 0.0081889389 | G20: ='Data Sheet'!F31/'Data Sheet'!F$17 -> 0.019133881 | H20: ='Data Sheet'!G31/'Data Sheet'!G$17 -> 0.025529559 | I20: ='Data Sheet'!H31/'Data Sheet'!H$17 -> 0.018066207 | J20: ='Data Sheet'!I31/'Data Sheet'!I$17 -> 0.019595779 | ... L20: ='Data Sheet'!K31/'Data Sheet'!K$17 -> 0.021494621
B24: ="Common Size Balance Sheet Statement" &" "&"-"&'Data Sheet'!B1 -> Common Size Balance Sheet Statement -TATA STEEL LTD
B26: Particular | C26: ='Data Sheet'!B16 -> 42825 | D26: ='Data Sheet'!C16 -> 43190 | E26: ='Data Sheet'!D16 -> 43555 | F26: ='Data Sheet'!E16 -> 43921 | G26: ='Data Sheet'!F16 -> 44286 | H26: ='Data Sheet'!G16 -> 44651 | I26: ='Data Sheet'!H16 -> 45016 | J26: ='Data Sheet'!I16 -> 45382 | ... L26: ='Data Sheet'!K16 -> 46112
B28: Total Liabalities | C28: ='Data Sheet'!B61/'Data Sheet'!B$61 -> 1 | D28: ='Data Sheet'!C61/'Data Sheet'!C$61 -> 1 | E28: ='Data Sheet'!D61/'Data Sheet'!D$61 -> 1 | F28: ='Data Sheet'!E61/'Data Sheet'!E$61 -> 1 | G28: ='Data Sheet'!F61/'Data Sheet'!F$61 -> 1 | H28: ='Data Sheet'!G61/'Data Sheet'!G$61 -> 1 | I28: ='Data Sheet'!H61/'Data Sheet'!H$61 -> 1 | J28: ='Data Sheet'!I61/'Data Sheet'!I$61 -> 1 | ... L28: ='Data Sheet'!K61/'Data Sheet'!K$61 -> 1
B29: ='Data Sheet'!A57 -> Equity Share Capital | C29: ='Data Sheet'!B57/'Data Sheet'!B$61 -> 0.0056262963 | D29: ='Data Sheet'!C57/'Data Sheet'!C$61 -> 0.0054855225 | E29: ='Data Sheet'!D57/'Data Sheet'!D$61 -> 0.0049186883 | F29: ='Data Sheet'!E57/'Data Sheet'!E$61 -> 0.0045954407 | G29: ='Data Sheet'!F57/'Data Sheet'!F$61 -> 0.0049100651 | H29: ='Data Sheet'!G57/'Data Sheet'!G$61 -> 0.0043240662 | I29: ='Data Sheet'!H57/'Data Sheet'!H$61 -> 0.0042791102 | J29: ='Data Sheet'!I57/'Data Sheet'!I$61 -> 0.0046319438 | ... L29: ='Data Sheet'!K57/'Data Sheet'!K$61 -> 0.0042070101
B30: ='Data Sheet'!A58 -> Reserves | C30: ='Data Sheet'!B58/'Data Sheet'!B$61 -> 0.21368305 | D30: ='Data Sheet'!C58/'Data Sheet'!C$61 -> 0.28614918 | E30: ='Data Sheet'!D58/'Data Sheet'!D$61 -> 0.29118503 | F30: ='Data Sheet'!E58/'Data Sheet'!E$61 -> 0.29071485 | G30: ='Data Sheet'!F58/'Data Sheet'!F$61 -> 0.29946047 | H30: ='Data Sheet'!G58/'Data Sheet'!G$61 -> 0.4008964 | I30: ='Data Sheet'!H58/'Data Sheet'!H$61 -> 0.35691088 | J30: ='Data Sheet'!I58/'Data Sheet'!I$61 -> 0.33711152 | ... L30: ='Data Sheet'!K58/'Data Sheet'!K$61 -> 0.34035492
B31: ='Data Sheet'!A59 -> Borrowings | C31: ='Data Sheet'!B59/'Data Sheet'!B$61 -> 0.48139029 | D31: ='Data Sheet'!C59/'Data Sheet'!C$61 -> 0.44148191 | E31: ='Data Sheet'!D59/'Data Sheet'!D$61 -> 0.43310878 | F31: ='Data Sheet'!E59/'Data Sheet'!E$61 -> 0.46690191 | G31: ='Data Sheet'!F59/'Data Sheet'!F$61 -> 0.36284574 | H31: ='Data Sheet'!G59/'Data Sheet'!G$61 -> 0.26754799 | I31: ='Data Sheet'!H59/'Data Sheet'!H$61 -> 0.29745727 | J31: ='Data Sheet'!I59/'Data Sheet'!I$61 -> 0.32334981 | ... L31: ='Data Sheet'!K59/'Data Sheet'!K$61 -> 0.3115586
B32: ='Data Sheet'!A60 -> Other Liabilities | C32: ='Data Sheet'!B60/'Data Sheet'!B$61 -> 0.29930036 | D32: ='Data Sheet'!C60/'Data Sheet'!C$61 -> 0.26688338 | E32: ='Data Sheet'!D60/'Data Sheet'!D$61 -> 0.27078751 | F32: ='Data Sheet'!E60/'Data Sheet'!E$61 -> 0.2377878 | G32: ='Data Sheet'!F60/'Data Sheet'!F$61 -> 0.33278373 | H32: ='Data Sheet'!G60/'Data Sheet'!G$61 -> 0.32723155 | I32: ='Data Sheet'!H60/'Data Sheet'!H$61 -> 0.34135273 | J32: ='Data Sheet'!I60/'Data Sheet'!I$61 -> 0.33490672 | ... L32: ='Data Sheet'!K60/'Data Sheet'!K$61 -> 0.34387947
B34: ='Data Sheet'!A61&" "& "Assets" -> Total Assets | C34: ='Data Sheet'!B66/'Data Sheet'!B$66 -> 1 | D34: ='Data Sheet'!C66/'Data Sheet'!C$66 -> 1 | E34: ='Data Sheet'!D66/'Data Sheet'!D$66 -> 1 | F34: ='Data Sheet'!E66/'Data Sheet'!E$66 -> 1 | G34: ='Data Sheet'!F66/'Data Sheet'!F$66 -> 1 | H34: ='Data Sheet'!G66/'Data Sheet'!G$66 -> 1 | I34: ='Data Sheet'!H66/'Data Sheet'!H$66 -> 1 | J34: ='Data Sheet'!I66/'Data Sheet'!I$66 -> 1 | ... L34: ='Data Sheet'!K66/'Data Sheet'!K$66 -> 1
B35: ='Data Sheet'!A62 -> Net Block | C35: ='Data Sheet'!B62/'Data Sheet'!B$66 -> 0.53353409 | D35: ='Data Sheet'!C62/'Data Sheet'!C$66 -> 0.46044416 | E35: ='Data Sheet'!D62/'Data Sheet'!D$66 -> 0.53460528 | F35: ='Data Sheet'!E62/'Data Sheet'!E$66 -> 0.54004068 | G35: ='Data Sheet'!F62/'Data Sheet'!F$66 -> 0.55666283 | H35: ='Data Sheet'!G62/'Data Sheet'!G$66 -> 0.47194619 | I35: ='Data Sheet'!H62/'Data Sheet'!H$66 -> 0.51374782 | J35: ='Data Sheet'!I62/'Data Sheet'!I$66 -> 0.55257154 | ... L35: ='Data Sheet'!K62/'Data Sheet'!K$66 -> 0.60674286
B36: ='Data Sheet'!A63 -> Capital Work in Progress | C36: ='Data Sheet'!B63/'Data Sheet'!B$66 -> 0.091530129 | D36: ='Data Sheet'!C63/'Data Sheet'!C$66 -> 0.079600612 | E36: ='Data Sheet'!D63/'Data Sheet'!D$66 -> 0.080083063 | F36: ='Data Sheet'!E63/'Data Sheet'!E$66 -> 0.078253658 | G36: ='Data Sheet'!F63/'Data Sheet'!F$66 -> 0.077928183 | H36: ='Data Sheet'!G63/'Data Sheet'!G$66 -> 0.078058989 | I36: ='Data Sheet'!H63/'Data Sheet'!H$66 -> 0.10936749 | J36: ='Data Sheet'!I63/'Data Sheet'!I$66 -> 0.12756757 | ... L36: ='Data Sheet'!K63/'Data Sheet'!K$66 -> 0.096105582
B37: ='Data Sheet'!A64 -> Investments | C37: ='Data Sheet'!B64/'Data Sheet'!B$66 -> 0.072237228 | D37: ='Data Sheet'!C64/'Data Sheet'!C$66 -> 0.085757409 | E37: ='Data Sheet'!D64/'Data Sheet'!D$66 -> 0.024651309 | F37: ='Data Sheet'!E64/'Data Sheet'!E$66 -> 0.025226579 | G37: ='Data Sheet'!F64/'Data Sheet'!F$66 -> 0.043794701 | H37: ='Data Sheet'!G64/'Data Sheet'!G$66 -> 0.046525644 | I37: ='Data Sheet'!H64/'Data Sheet'!H$66 -> 0.029468936 | J37: ='Data Sheet'!I64/'Data Sheet'!I$66 -> 0.023235356 | ... L37: ='Data Sheet'!K64/'Data Sheet'!K$66 -> 0.023907253
B38: ='Data Sheet'!A65 -> Other Assets | C38: ='Data Sheet'!B75/'Data Sheet'!B$66 -> 0.063137408 | D38: ='Data Sheet'!C75/'Data Sheet'!C$66 -> 0.14094796 | E38: ='Data Sheet'!D75/'Data Sheet'!D$66 -> 0.1595701 | F38: ='Data Sheet'!E75/'Data Sheet'!E$66 -> 0.16780352 | G38: ='Data Sheet'!F75/'Data Sheet'!F$66 -> 0.12236636 | H38: ='Data Sheet'!G75/'Data Sheet'!G$66 -> 0.13093432 | I38: ='Data Sheet'!H75/'Data Sheet'!H$66 -> 0.081014372 | J38: ='Data Sheet'!I75/'Data Sheet'!I$66 -> 0.058616606 | ... L38: ='Data Sheet'!K75/'Data Sheet'!K$66 -> 0.063394142
B39: ='Data Sheet'!A67 -> Receivables | C39: ='Data Sheet'!B67/'Data Sheet'!B$66 -> 0.067190471 | D39: ='Data Sheet'!C67/'Data Sheet'!C$66 -> 0.059483484 | E39: ='Data Sheet'!D67/'Data Sheet'!D$66 -> 0.050740325 | F39: ='Data Sheet'!E67/'Data Sheet'!E$66 -> 0.031647352 | G39: ='Data Sheet'!F67/'Data Sheet'!F$66 -> 0.039112261 | H39: ='Data Sheet'!G67/'Data Sheet'!G$66 -> 0.043362218 | I39: ='Data Sheet'!H67/'Data Sheet'!H$66 -> 0.028932593 | J39: ='Data Sheet'!I67/'Data Sheet'!I$66 -> 0.023257487 | ... L39: ='Data Sheet'!K67/'Data Sheet'!K$66 -> 0.016582285
B40: ='Data Sheet'!A68 -> Inventory | C40: ='Data Sheet'!B68/'Data Sheet'!B$66 -> 0.14383414 | D40: ='Data Sheet'!C68/'Data Sheet'!C$66 -> 0.13573567 | E40: ='Data Sheet'!D68/'Data Sheet'!D$66 -> 0.13599533 | F40: ='Data Sheet'!E68/'Data Sheet'!E$66 -> 0.1246993 | G40: ='Data Sheet'!F68/'Data Sheet'!F$66 -> 0.13642938 | H40: ='Data Sheet'!G68/'Data Sheet'!G$66 -> 0.17287763 | I40: ='Data Sheet'!H68/'Data Sheet'!H$66 -> 0.1906662 | J40: ='Data Sheet'!I68/'Data Sheet'!I$66 -> 0.18252968 | ... L40: ='Data Sheet'!K68/'Data Sheet'!K$66 -> 0.1593487
B41: ='Data Sheet'!A69 -> Cash & Bank | C41: ='Data Sheet'!B69/'Data Sheet'!B$66 -> 0.028536533 | D41: ='Data Sheet'!C69/'Data Sheet'!C$66 -> 0.038030704 | E41: ='Data Sheet'!D69/'Data Sheet'!D$66 -> 0.014354602 | F41: ='Data Sheet'!E69/'Data Sheet'!E$66 -> 0.032328912 | G41: ='Data Sheet'!F69/'Data Sheet'!F$66 -> 0.023706282 | H41: ='Data Sheet'!G69/'Data Sheet'!G$66 -> 0.056295007 | I41: ='Data Sheet'!H69/'Data Sheet'!H$66 -> 0.046802584 | J41: ='Data Sheet'!I69/'Data Sheet'!I$66 -> 0.032221759 | ... L41: ='Data Sheet'!K69/'Data Sheet'!K$66 -> 0.033919171

Sheet Raw FS
B4: Particular | C4: 42064 | D4: 42430 | E4: 42795 | F4: 43160 | G4: 43525 | H4: 43891 | I4: 44256 | J4: 44621 | K4: 44986 | L4: 45352 | M4: 45717 | N4: 46082
B5: Equity Capital | C5: 971 | D5: 970 | E5: 970 | F5: 1145 | G5: 1145 | H5: 1145 | I5: 1198 | J5: 1221 | K5: 1221 | L5: 1247 | M5: 1247 | N5: 1247
B6: Reserves | C6: 30378 | D6: 42762 | E6: 36849 | F6: 59726 | G6: 67780 | H6: 72431 | I6: 73041 | J6: 113222 | K6: 101861 | L6: 90788 | M6: 89922 | N6: 100920
B7: Total Borrowings
B8: Long term Borrowings | C8: 65675 | D8: 64873 | E8: 64022 | F8: 72789 | G8: 80343 | H8: 94105 | I8: 65698 | J8: 44764 | K8: 51446 | L8: 51577 | M8: 68552 | N8: 63754
B9: Short term Borrowings | C9: 9599 | D9: 15722 | E9: 18328 | F9: 15885 | G9: 10802 | H9: 19184 | I9: 14969 | J9: 24065 | K9: 26571 | L9: 29997 | M9: 20412 | N9: 21203
B10: Lease Liabilities | C10: 0 | D10: 0 | E10: 0 | F10: 0 | G10: 0 | H10: 0 | I10: 7834 | J10: 6733 | K10: 6875 | L10: 5508 | M10: 5837 | N10: 7425
B11: Preference Capital | C11: 0 | D11: 0 | E11: 0 | F11: 20 | G11: 13 | H11: 0 | I11: 0 | J11: 0 | K11: 0 | L11: 0 | M11: 0 | N11: 0
B12: Other Borrowings | C12: 5428 | D12: 1392 | E12: 664 | F12: 3453 | G12: 9658 | H12: 3039 | I12: 0 | J12: 0 | K12: 0 | L12: 0 | M12: 0 | N12: 0
B13: Other Liabilities
B14: Non controlling int | C14: 1704 | D14: 781 | E14: 1602 | F14: 937 | G14: 2364 | H14: 2587 | I14: 3270 | J14: 2655 | K14: 2093 | L14: 397 | M14: 183 | N14: 1613
B15: Trade Payables | C15: 19190 | D15: 18557 | E15: 18574 | F15: 20414 | G15: 21717 | H15: 21381 | I15: 25967 | J15: 36765 | K15: 37833 | L15: 30228 | M15: 29314 | N15: 34810
B16: Advance from Customers | C16: 367 | D16: 456 | E16: 566 | F16: 616 | G16: 819 | H16: 869 | I16: 2399 | J16: 3253 | K16: 3394 | L16: 2771 | M16: 1655 | N16: 2222
B17: Other liability items | C17: 25798 | D17: 31371 | E17: 30871 | F17: 33738 | G17: 38131 | H17: 34408 | I17: 49533 | J17: 49744 | K17: 54101 | L17: 56799 | M17: 58335 | N17: 63320
B18: Total Liabilities | C18: 159109 | D18: 176884 | E18: 172447 | F18: 208722 | G18: 232773 | H18: 249149 | I18: 243909 | J18: 282422 | K18: 285396 | L18: 269312 | M18: 275459 | N18: 296515
B20: Fixed Assets
B21: Land | C21: 2433 | D21: 16499 | E21: 16545 | F21: 16955 | G21: 17126 | H21: 19853 | I21: 20656 | J21: 20770 | K21: 21701 | L21: 22067 | M21: 22299 | N21: 23659
B22: Building | C22: 14186 | D22: 11058 | E22: 11141 | F22: 12148 | G22: 21753 | H22: 25883 | I22: 26828 | J22: 27588 | K22: 28904 | L22: 30173 | M22: 31819 | N22: 36997
B23: Plant Machinery | C23: 124249 | D23: 73865 | E23: 93462 | F23: 104889 | G23: 127435 | H23: 141914 | I23: 155596 | J23: 152754 | K23: 163134 | L23: 175111 | M23: 186115 | N23: 224912
B24: Equipments | C24: 403 | D24: 414 | E24: 543 | F24: 668 | G24: 739 | H24: 796 | I24: 0 | J24: 0 | K24: 0 | L24: 0 | M24: 0 | N24: 0
B25: Furniture n fittings | C25: 916 | D25: 0 | E25: 0 | F25: 0 | G25: 0 | H25: 19 | I25: 1047 | J25: 991 | K25: 1111 | L25: 1238 | M25: 1298 | N25: 1429
B26: Railway sidings | C26: 1239 | D26: 757 | E26: 1350 | F26: 1397 | G26: 1549 | H26: 1676 | I26: 1671 | J26: 1780 | K26: 1841 | L26: 1872 | M26: 1890 | N26: 2384
B27: Vehicles | C27: 376 | D27: 335 | E27: 352 | F27: 343 | G27: 398 | H27: 615 | I27: 681 | J27: 686 | K27: 749 | L27: 794 | M27: 830 | N27: 978
B28: Intangible Assets | C28: 13500 | D28: 6026 | E28: 4990 | F28: 5810 | G28: 4293 | H28: 5868 | I28: 6289 | J28: 6229 | K28: 7572 | L28: 7772 | M28: 7896 | N28: 10230
B29: Other fixed assets | C29: 7315 | D29: 5154 | E29: 2919 | F29: 3233 | G29: 3742 | H29: 4424 | I29: 5171 | J29: 10953 | K29: 20384 | L29: 20546 | M29: 20881 | N29: 22389
B30: Gross Block | C30: 164618 | D30: 114109 | E30: 131302 | F30: 145444 | G30: 177037 | H30: 201047 | I30: 217939 | J30: 221752 | K30: 245395 | L30: 259572 | M30: 273028 | N30: 322978
B31: Accumulated Depreciation | C31: 96518 | D31: 41909 | E31: 39295 | F31: 49339 | G31: 52595 | H31: 66496 | I31: 82164 | J31: 88464 | K31: 98773 | L31: 110758 | M31: 122114 | N31: 143070
B32: Net Block | C32: =C30-C31 -> 68100 | D32: =D30-D31 -> 72200 | E32: =E30-E31 -> 92007 | F32: =F30-F31 -> 96105 | G32: =G30-G31 -> 124442 | H32: =H30-H31 -> 134551 | I32: =I30-I31 -> 135775 | J32: =J30-J31 -> 133288 | ... N32: =N30-N31 -> 179908
B34: CWIP | C34: 28678 | D34: 35996 | E34: 15784 | F34: 16614 | G34: 18641 | H34: 19497 | I34: 19007 | J34: 22046 | K34: 31213 | L34: 34356 | M34: 41622 | N34: 28497
B35: Investments | C35: 3455 | D35: 10714 | E35: 12457 | F35: 17899 | G35: 5738 | H35: 6285 | I35: 10682 | J35: 13140 | K35: 8410 | L35: 6258 | M35: 6194 | N35: 7089
B37: Other Assets - | C37: 58876 | D37: 57974 | E37: 52200 | F37: 78103 | G37: 83952 | H37: 88816 | I37: 78445 | J37: 113948 | K37: 99151 | L37: 79885 | M37: 76728 | N37: 81021
B38: Inventories | C38: 25150 | D38: 20013 | E38: 24804 | F38: 28331 | G38: 31656 | H38: 31069 | I38: 33276 | J38: 48824 | K38: 54415 | L38: 49158 | M38: 44590 | N38: 47249
B39: Trade receivables | C39: 13310 | D39: 12066 | E39: 11587 | F39: 12416 | G39: 11811 | H39: 7885 | I39: 9540 | J39: 12246 | K39: 8257 | L39: 6264 | M39: 5260 | N39: 4917
B40: Receivables over 6m | C40: 443 | D40: 0 | E40: 0 | F40: 0 | G40: 0 | H40: 0 | I40: 620 | J40: 694 | K40: 1051 | L40: 608 | M40: 477 | N40: 679
B41: Receivables under 6m | C41: 13162 | D41: 12386 | E41: 11814 | F41: 12666 | G41: 12204 | H41: 8194 | I41: 9279 | J41: 11817 | K41: 7961 | L41: 5990 | M41: 5066 | N41: 4584
B42: Prov for Doubtful | C42: -295 | D42: -320 | E42: -227 | F42: -250 | G42: -393 | H42: -309 | I42: -360 | J42: -265 | K42: -755 | L42: -335 | M42: -283 | N42: -347
B43: Cash Equivalents | C43: 8750 | D43: 6186 | E43: 4921 | F43: 7938 | G43: 3341 | H43: 8055 | I43: 5782 | J43: 15899 | K43: 13357 | L43: 8678 | M43: 11647 | N43: 10058
B44: Loans n Advances | C44: -182 | D44: 107 | E44: 98 | F44: 219 | G44: -56 | H44: 195 | I44: -193 | J44: -158 | K44: -90 | L44: -56 | M44: 49 | N44: 1167
B45: Other asset items | C45: 11848 | D45: 19602 | E45: 10790 | F45: 29200 | G45: 37200 | H45: 41613 | I45: 30039 | J45: 37137 | K45: 23211 | L45: 15842 | M45: 15182 | N45: 17630
B46: Total Assets | C46: 159109 | D46: 176884 | E46: 172447 | F46: 208722 | G46: 232773 | H46: 249149 | I46: 243909 | J46: 282422 | K46: 285396 | L46: 269312 | M46: 275459 | N46: 296515

Sheet Intrinsic Growth
B4: Calculation ROIC | C4: ='Raw FS'!J4 -> 44621 | D4: ='Raw FS'!K4 -> 44986 | E4: ='Raw FS'!L4 -> 45352 | F4: ='Raw FS'!M4 -> 45717 | G4: ='Raw FS'!N4 -> 46082
B6: Current Assets
B7: ='Raw FS'!B38 -> Inventories | C7: =IFERROR('Raw FS'!J38,0) -> 48824 | D7: =IFERROR('Raw FS'!K38,0) -> 54415 | E7: =IFERROR('Raw FS'!L38,0) -> 49158 | F7: =IFERROR('Raw FS'!M38,0) -> 44590 | G7: =IFERROR('Raw FS'!N38,0) -> 47249
B8: ='Raw FS'!B39 -> Trade receivables | C8: =IFERROR('Raw FS'!J39,0) -> 12246 | D8: =IFERROR('Raw FS'!K39,0) -> 8257 | E8: =IFERROR('Raw FS'!L39,0) -> 6264 | F8: =IFERROR('Raw FS'!M39,0) -> 5260 | G8: =IFERROR('Raw FS'!N39,0) -> 4917
B9: ='Raw FS'!B40 -> Receivables over 6m | C9: =IFERROR('Raw FS'!J40,0) -> 694 | D9: =IFERROR('Raw FS'!K40,0) -> 1051 | E9: =IFERROR('Raw FS'!L40,0) -> 608 | F9: =IFERROR('Raw FS'!M40,0) -> 477 | G9: =IFERROR('Raw FS'!N40,0) -> 679
B10: ='Raw FS'!B41 -> Receivables under 6m | C10: =IFERROR('Raw FS'!J41,0) -> 11817 | D10: =IFERROR('Raw FS'!K41,0) -> 7961 | E10: =IFERROR('Raw FS'!L41,0) -> 5990 | F10: =IFERROR('Raw FS'!M41,0) -> 5066 | G10: =IFERROR('Raw FS'!N41,0) -> 4584
B11: ='Raw FS'!B44 -> Loans n Advances | C11: =IFERROR('Raw FS'!J44,0) -> -158 | D11: =IFERROR('Raw FS'!K44,0) -> -90 | E11: =IFERROR('Raw FS'!L44,0) -> -56 | F11: =IFERROR('Raw FS'!M44,0) -> 49 | G11: =IFERROR('Raw FS'!N44,0) -> 1167
B12: ='Raw FS'!B45 -> Other asset items | C12: =IFERROR('Raw FS'!J45,0) -> 37137 | D12: =IFERROR('Raw FS'!K45,0) -> 23211 | E12: =IFERROR('Raw FS'!L45,0) -> 15842 | F12: =IFERROR('Raw FS'!M45,0) -> 15182 | G12: =IFERROR('Raw FS'!N45,0) -> 17630
B13: Total Current Assets | C13: =SUM(C7:C12) -> 110560 | D13: =SUM(D7:D12) -> 94805 | E13: =SUM(E7:E12) -> 77806 | F13: =SUM(F7:F12) -> 70624 | G13: =SUM(G7:G12) -> 76226
B16: Current Liabilites
B17: ='Raw FS'!B15 -> Trade Payables | C17: ='Raw FS'!J15 -> 36765 | D17: ='Raw FS'!K15 -> 37833 | E17: ='Raw FS'!L15 -> 30228 | F17: ='Raw FS'!M15 -> 29314 | G17: ='Raw FS'!N15 -> 34810
B18: ='Raw FS'!B16 -> Advance from Customers | C18: ='Raw FS'!J16 -> 3253 | D18: ='Raw FS'!K16 -> 3394 | E18: ='Raw FS'!L16 -> 2771 | F18: ='Raw FS'!M16 -> 1655 | G18: ='Raw FS'!N16 -> 2222
B19: ='Raw FS'!B17 -> Other liability items | C19: ='Raw FS'!J17 -> 49744 | D19: ='Raw FS'!K17 -> 54101 | E19: ='Raw FS'!L17 -> 56799 | F19: ='Raw FS'!M17 -> 58335 | G19: ='Raw FS'!N17 -> 63320
B20: Total Current Liabilities | C20: =SUM(C17:C19) -> 89762 | D20: =SUM(D17:D19) -> 95328 | E20: =SUM(E17:E19) -> 89798 | F20: =SUM(F17:F19) -> 89304 | G20: =SUM(G17:G19) -> 100352
A22: # | B22: Net Working Capital | C22: =C13-C20 -> 20798 | D22: =D13-D20 -> -523 | E22: =E13-E20 -> -11992 | F22: =F13-F20 -> -18680 | G22: =G13-G20 -> -24126
B25: Non-Current Assets
B26: ='Raw FS'!B21 -> Land | C26: ='Raw FS'!J21 -> 20770 | D26: ='Raw FS'!K21 -> 21701 | E26: ='Raw FS'!L21 -> 22067 | F26: ='Raw FS'!M21 -> 22299 | G26: ='Raw FS'!N21 -> 23659
B27: ='Raw FS'!B22 -> Building | C27: ='Raw FS'!J22 -> 27588 | D27: ='Raw FS'!K22 -> 28904 | E27: ='Raw FS'!L22 -> 30173 | F27: ='Raw FS'!M22 -> 31819 | G27: ='Raw FS'!N22 -> 36997
B28: ='Raw FS'!B23 -> Plant Machinery | C28: ='Raw FS'!J23 -> 152754 | D28: ='Raw FS'!K23 -> 163134 | E28: ='Raw FS'!L23 -> 175111 | F28: ='Raw FS'!M23 -> 186115 | G28: ='Raw FS'!N23 -> 224912
B29: ='Raw FS'!B24 -> Equipments | C29: ='Raw FS'!J24 -> 0 | D29: ='Raw FS'!K24 -> 0 | E29: ='Raw FS'!L24 -> 0 | F29: ='Raw FS'!M24 -> 0 | G29: ='Raw FS'!N24 -> 0
B30: ='Raw FS'!B25 -> Furniture n fittings | C30: ='Raw FS'!J25 -> 991 | D30: ='Raw FS'!K25 -> 1111 | E30: ='Raw FS'!L25 -> 1238 | F30: ='Raw FS'!M25 -> 1298 | G30: ='Raw FS'!N25 -> 1429
B31: ='Raw FS'!B26 -> Railway sidings | C31: ='Raw FS'!J26 -> 1780 | D31: ='Raw FS'!K26 -> 1841 | E31: ='Raw FS'!L26 -> 1872 | F31: ='Raw FS'!M26 -> 1890 | G31: ='Raw FS'!N26 -> 2384
B32: ='Raw FS'!B27 -> Vehicles | C32: ='Raw FS'!J27 -> 686 | D32: ='Raw FS'!K27 -> 749 | E32: ='Raw FS'!L27 -> 794 | F32: ='Raw FS'!M27 -> 830 | G32: ='Raw FS'!N27 -> 978
B33: ='Raw FS'!B28 -> Intangible Assets | C33: ='Raw FS'!J28 -> 6229 | D33: ='Raw FS'!K28 -> 7572 | E33: ='Raw FS'!L28 -> 7772 | F33: ='Raw FS'!M28 -> 7896 | G33: ='Raw FS'!N28 -> 10230
B34: ='Raw FS'!B29 -> Other fixed assets | C34: ='Raw FS'!J29 -> 10953 | D34: ='Raw FS'!K29 -> 20384 | E34: ='Raw FS'!L29 -> 20546 | F34: ='Raw FS'!M29 -> 20881 | G34: ='Raw FS'!N29 -> 22389
B35: ='Raw FS'!B30 -> Gross Block | C35: =SUM(C26:C34) -> 221751 | D35: =SUM(D26:D34) -> 245396 | E35: =SUM(E26:E34) -> 259573 | F35: =SUM(F26:F34) -> 273028 | G35: =SUM(G26:G34) -> 322978
B36: ='Raw FS'!B31 -> Accumulated Depreciation | C36: =-'Raw FS'!J31 -> -88464 | D36: =-'Raw FS'!K31 -> -98773 | E36: =-'Raw FS'!L31 -> -110758 | F36: =-'Raw FS'!M31 -> -122114 | G36: =-'Raw FS'!N31 -> -143070
A37: # | B37: Net Non-Current Assets | C37: =SUM(C35:C36) -> 133287 | D37: =SUM(D35:D36) -> 146623 | E37: =SUM(E35:E36) -> 148815 | F37: =SUM(F35:F36) -> 150914 | G37: =SUM(G35:G36) -> 179908
A40: # | B40: Invested Capital | C40: =C22+C37 -> 154085 | D40: =D22+D37 -> 146100 | E40: =E22+E37 -> 136823 | F40: =F22+F37 -> 132234 | G40: =G22+G37 -> 155782
B41: EBIT | C41: ='HistoricalFS '!H17-'HistoricalFS '!H23 -> 54389.08 | D41: ='HistoricalFS '!I17-'HistoricalFS '!I23 -> 22964.96 | E41: ='HistoricalFS '!J17-'HistoricalFS '!J23 -> 12365.76 | F41: ='HistoricalFS '!K17-'HistoricalFS '!K23 -> 14877.12 | G41: ='HistoricalFS '!L17-'HistoricalFS '!L23 -> 22397.93
A43: # | B43: ROIC | C43: =C41/C40 -> 0.35298102 | D43: =D41/D40 -> 0.15718658 | E43: =E41/E40 -> 0.090377787 | F43: =F41/F40 -> 0.11250601 | G43: =G41/G40 -> 0.14377739
B46: Calculation of Reinvestment Rate | C46: =C4 -> 44621 | D46: =D4 -> 44986 | E46: =E4 -> 45352 | F46: =F4 -> 45717 | G46: =G4 -> 46082
B48: Net Capex | C48: =-SUM('Cash Flow Data'!J12:J13) -> 9953 | D48: =-SUM('Cash Flow Data'!K12:K13) -> 13814 | E48: =-SUM('Cash Flow Data'!L12:L13) -> 17732 | F48: =-SUM('Cash Flow Data'!M12:M13) -> 14407 | G48: =-SUM('Cash Flow Data'!N12:N13) -> 13158
B49: Change In working Capital | D49: =(D22-C22) -> -21321 | E49: =(E22-D22) -> -11469 | F49: =(F22-E22) -> -6688 | G49: =(G22-F22) -> -5446
B51: EBIT | C51: =C41 -> 54389.08 | D51: =D41 -> 22964.96 | E51: =E41 -> 12365.76 | F51: =F41 -> 14877.12 | G51: =G41 -> 22397.93
B52: Marginal Tax Rate | C52: 0.25 | D52: =C52 -> 0.25 | E52: =D52 -> 0.25 | F52: =E52 -> 0.25 | G52: =F52 -> 0.25
B53: EBIT(1-Tax) | C53: =C51*(1-C52) -> 40791.81 | D53: =D51*(1-D52) -> 17223.72 | E53: =E51*(1-E52) -> 9274.32 | F53: =F51*(1-F52) -> 11157.84 | G53: =G51*(1-G52) -> 16798.448
B55: Reinvestment | D55: =SUM(D48:D49) -> -7507 | E55: =SUM(E48:E49) -> 6263 | F55: =SUM(F48:F49) -> 7719 | G55: =SUM(G48:G49) -> 7712
B57: Reinvestment Rate | D57: =D55/D53 -> -0.43585242 | E57: =E55/E53 -> 0.67530557 | F57: =F55/F53 -> 0.69180056 | G57: =G55/G53 -> 0.45909004
F59: Average | G59: =AVERAGE(D57:G57) -> 0.34758594
F60: Median | G60: =MEDIAN(D57:G57) -> 0.56719781
B63: Calculation Of Growth | C63: =C4 -> 44621 | D63: =D4 -> 44986 | E63: =E4 -> 45352 | F63: =F4 -> 45717 | G63: =G4 -> 46082
B65: =B57 -> Reinvestment Rate | D65: =D57 -> -0.43585242 | E65: =E57 -> 0.67530557 | F65: =F57 -> 0.69180056 | G65: =G57 -> 0.45909004
B66: =B43 -> ROIC | D66: =D43 -> 0.15718658 | E66: =E43 -> 0.090377787 | F66: =F43 -> 0.11250601 | G66: =G43 -> 0.14377739
B68: Intrinsic Growth | D68: =D65*D66 -> -0.068510153 | E68: =E65*E66 -> 0.061032624 | F68: =F65*F66 -> 0.077831723 | G68: =G65*G66 -> 0.06600677
F70: Average | G70: =AVERAGE(D68:G68) -> 0.034090241
F71: Median | G71: =MEDIAN(D68:G68) -> 0.063519697

Sheet DCF
B3: Calculation of PV of FCFF | C3: ='Intrinsic Growth'!G4 -> 46082 | D3: =C3+365 -> 46447 | E3: =D3+366 -> 46813 | F3: =E3+365 -> 47178 | G3: =F3+365 -> 47543 | H3: =G3+365 -> 47908
B5: EBIT | C5: ='Data Sheet'!K37-'Data Sheet'!K26 -> 23043.8 | D5: =C5*(1+$C$16) -> 24507.535 | E5: =D5*(1+$C$16) -> 26064.246 | F5: =E5*(1+$C$16) -> 27719.839 | G5: =F5*(1+$C$16) -> 29480.595 | H5: =G5*(1+$C$16) -> 31353.194
B6: Tax | C6: 0.25 | D6: =C6 -> 0.25 | E6: =D6 -> 0.25 | F6: =E6 -> 0.25 | G6: =F6 -> 0.25 | H6: =G6 -> 0.25
B7: EBIT(1-Tax) | C7: =C5*(1-C6) -> 17282.85 | D7: =D5*(1-D6) -> 18380.651 | E7: =E5*(1-E6) -> 19548.185 | F7: =F5*(1-F6) -> 20789.88 | G7: =G5*(1-G6) -> 22110.446 | H7: =H5*(1-H6) -> 23514.895
B8: Less: Reinvestment Rate | C8: ='Intrinsic Growth'!G60 -> 0.56719781 | D8: =C8 -> 0.56719781 | E8: =D8 -> 0.56719781 | F8: =E8 -> 0.56719781 | G8: =F8 -> 0.56719781 | H8: =G8 -> 0.56719781
B9: Free Cash Flow to Firm(FCFF) | C9: =C7*(1-C8) -> 7480.0553 | D9: =D7*(1-D8) -> 7955.1862 | E9: =E7*(1-E8) -> 8460.4972 | F9: =F7*(1-F8) -> 8997.9054 | G9: =G7*(1-G8) -> 9569.4496 | H9: =H7*(1-H8) -> 10177.298
B10: Mid Year Convention | D10: 0.5 | E10: =D10+1 -> 1.5 | F10: =E10+1 -> 2.5 | G10: =F10+1 -> 3.5 | H10: =G10+1 -> 4.5
B11: Discounting Factor | D11: =1/(1+$C$18)^D10 -> 0.94882693 | E11: =1/(1+$C$18)^E10 -> 0.85420284 | F11: =1/(1+$C$18)^F10 -> 0.76901537 | G11: =1/(1+$C$18)^G10 -> 0.69232343 | H11: =1/(1+$C$18)^H10 -> 0.62327978
B13: Pv of FCFF | D13: =D9*D11 -> 7548.0949 | E13: =E9*E11 -> 7226.9808 | F13: =F9*F11 -> 6919.5276 | G13: =G9*G11 -> 6625.1542 | H13: =H9*H11 -> 6343.3041
B16: Expected Growth | C16: ='Intrinsic Growth'!G71 -> 0.063519697
B17: Terminal Growth | C17: 0.06 | F17: Calculation Of Sensitivity Analysis
B18: WACC | C18: =WACC!I41 -> 0.11077473 | F18: =C27 -> 213172.11 | G18: 0.09 | H18: 0.1 | I18: =C18 -> 0.11077473 | J18: 0.12 | K18: 0.13
F19: 0.04 | G19: 216475.14 | H19: 180395.95 | I19: 152932.5 | J19: 135296.96 | K19: 120263.97
F20: 0.05 | G20: 270593.93 | H20: 216475.14 | I20: 178096.33 | J20: 154625.1 | K20: 135296.96
B21: Calculation Of Terminal value | F21: 0.06 | G21: 360791.9 | H21: 270593.93 | I21: 213172.11 | J21: 180395.95 | K21: 154625.1
F22: 0.07 | G22: 541187.85 | H22: 360791.9 | I22: 265452.56 | J22: 216475.14 | K22: 180395.95
B23: FCFF(n+1) | C23: =H9*(1+C16) -> 10823.757
B24: WACC | C24: =C18 -> 0.11077473
B25: Terminal Growth Rate | C25: =C17 -> 0.06
B27: Terminal Value | C27: =C23/(C24-C25) -> 213172.11
B30: Calculation Of Equity Value Per Share
B32: PV of FCFF | C32: =SUM(D13:H13) -> 34663.062
B33: Present Value of Terminal Value | C33: =C27*H11 -> 132865.87
B34: Value of Operating Assets | C34: =SUM(C32:C33) -> 167528.93
B36: Add: Cash | C36: ='Raw FS'!N43 -> 10058
B37: Less: Debt | C37: =SUM('Raw FS'!N8:N9) -> 84957
B38: Value of Equity | C38: =C34+C36-C37 -> 92629.929
B39: No. of Share | C39: ='Data Sheet'!B6 -> 1248.3526
B41: Equity Value Per Share | C41: =C38/C39 -> 74.201735

Sheet Relative Pricing
B5: Amount in Crores
B6: Comparable Company Valuation
D7: Market Data | J7: Financials | N7: Valuation
B8: Company | C8: Ticker | D8: Share Price | E8: Share Outstanding | F8: Equity Value | G8: Net debt | H8: Enterprise value | J8: Revenue | K8: EBITDA | L8: Net Income | N8: EV/Revenue | O8: EV/EBITDA | P8: P/E
B9: =Data!C4 -> Tata Steel | D9: =Data!D4 -> 184.15 | E9: =Data!E4 -> 1248.35 | F9: =E9*D9 -> 229883.65 | G9: =Data!I4 -> 82324.15 | H9: =Data!J4 -> 312207.8 | J9: =Data!L4 -> 239756.11 | K9: =Data!N4 -> 2573719.7 | L9: =Data!O4 -> 11263.7 | N9: =H9/J9 -> 1.3021891 | O9: =H9/K9 -> 0.12130606 | P9: =F9/L9 -> 20.409249
B10: =Data!C5 -> JSW Steel | D10: =Data!D5 -> 1297.3 | E10: =Data!E5 -> 244.55 | F10: =E10*D10 -> 317254.72 | G10: =Data!I5 -> 58321 | H10: =Data!J5 -> 375575.72 | J10: =Data!L5 -> 189687 | K10: =Data!N5 -> 4295536.9 | L10: =Data!O5 -> 27995 | N10: =H10/J10 -> 1.979976 | O10: =H10/K10 -> 0.08743394 | P10: =F10/L10 -> 11.332549
B11: =Data!C6 -> Jindal Steel | D11: =Data!D6 -> 1136.3 | E11: =Data!E6 -> 102.01 | F11: =E11*D11 -> 115913.96 | G11: =Data!I6 -> 18467.95 | H11: =Data!J6 -> 134381.91 | J11: =Data!L6 -> 56412.57 | K11: =Data!N6 -> 1884727.7 | L11: =Data!O6 -> 2708.7 | N11: =H11/J11 -> 2.3821271 | O11: =H11/K11 -> 0.071300438 | P11: =F11/L11 -> 42.793208
B12: =Data!C7 -> S A I L | D12: =Data!D7 -> 186.1 | E12: =Data!E7 -> 413.05 | F12: =E12*D12 -> 76868.605 | G12: =Data!I7 -> 31195.2 | H12: =Data!J7 -> 108063.81 | J12: =Data!L7 -> 111134.75 | K12: =Data!N7 -> 794272.46 | L12: =Data!O7 -> 4272.27 | N12: =H12/J12 -> 0.97236737 | O12: =H12/K12 -> 0.13605382 | P12: =F12/L12 -> 17.99245
B13: =Data!C8 -> Jindal Stain. | D13: =Data!D8 -> 738.75 | E13: =Data!E8 -> 82.44 | F13: =E13*D13 -> 60902.55 | G13: =Data!I8 -> 4526.3 | H13: =Data!J8 -> 65428.85 | J13: =Data!L8 -> 44026.06 | K13: =Data!N8 -> 707732.3 | L13: =Data!O8 -> 3238.57 | N13: =H13/J13 -> 1.4861391 | O13: =H13/K13 -> 0.092448585 | P13: =F13/L13 -> 18.805383
B15: High | N15: =MAX(N9:N12) -> 2.3821271 | O15: =MAX(O9:O12) -> 0.13605382 | P15: =MAX(P9:P12) -> 42.793208
B16: 75 percentile | N16: =QUARTILE(N9:N12,3) -> 2.0805138 | O16: =QUARTILE(O9:O12,3) -> 0.124993 | P16: =QUARTILE(P9:P12,3) -> 26.005238
B17: Average | N17: =AVERAGE(N9:N13) -> 1.6245598 | O17: =AVERAGE(O9:O13) -> 0.10170857 | P17: =AVERAGE(P9:P13) -> 22.266568
B18: Median | N18: =MEDIAN(N9:N13) -> 1.4861391 | O18: =MEDIAN(O9:O13) -> 0.092448585 | P18: =MEDIAN(P9:P13) -> 18.805383
B19: 25 percentile | N19: =QUARTILE(N9:N13,1) -> 1.3021891 | O19: =QUARTILE(O9:O13,1) -> 0.08743394 | P19: =QUARTILE(P9:P13,1) -> 17.99245
B20: Low | N20: =MIN(N9:N13) -> 0.97236737 | O20: =MIN(O9:O13) -> 0.071300438 | P20: =MIN(P9:P13) -> 11.332549
B23: Tata Steel ltd Comparable Valuation | N23: EV/Revenue | O23: EV/EBITDA | P23: P/E
B24: Implied Enterprise Value | N24: =N18*J9 -> 356310.93 | O24: =O18*K9 -> 237936.74 | P24: =P26+P25 -> 294142.35
B25: Net Debt | N25: =G9 -> 82324.15 | O25: =N25 -> 82324.15 | P25: =O25 -> 82324.15
B26: Implied Market Value | N26: =N24-N25 -> 273986.78 | O26: =O24-O25 -> 155612.59 | P26: =P18*L9 -> 211818.2
B27: =E8 -> Share Outstanding | N27: =$E$9 -> 1248.35 | O27: =$E$9 -> 1248.35 | P27: =$E$9 -> 1248.35
B29: Implied Value per Share | N29: =N26/N27 -> 219.47914 | O29: =O26/O27 -> 124.65462 | P29: =P26/P27 -> 169.67853
N31: =IF(N29>$D$9,"Undervalued","Overvalued") -> Undervalued | O31: =IF(O29>$D$9,"Undervalued","Overvalued") -> Overvalued | P31: =IF(P29>$D$9,"Undervalued","Overvalued") -> Overvalued

Sheet Data
B3: S.No. | C3: Company | D3: CMP Rs. | E3: No. Eq. Shares Cr. | G3: Debt Rs.Cr. | H3: Cash End Rs.Cr. | I3: net debt | J3: EV | K3: EV Rs.Cr. | L3: Sales Rs.Cr. | M3: EV / EBITDA | N3: EBITDA | O3: Net Profit
B4: 2 | C4: Tata Steel | D4: 184.15 | E4: 1248.35 | F4: =E4*D4 -> 229883.65 | G4: 92381.68 | H4: 10057.53 | I4: =G4-H4 -> 82324.15 | J4: =G4+F4-H4 -> 312207.8 | K4: 312344.62 | L4: 239756.11 | M4: 8.24 | N4: =M4*K4 -> 2573719.7 | O4: 11263.7
B5: 1 | C5: JSW Steel | D5: 1297.3 | E5: 244.55 | F5: =E5*D5 -> 317254.72 | G5: 99310 | H5: 40989 | I5: =G5-H5 -> 58321 | J5: =G5+F5-H5 -> 375575.72 | K5: 375156.06 | L5: 189687 | M5: 11.45 | N5: =M5*K5 -> 4295536.9 | O5: 27995
B6: 3 | C6: Jindal Steel | D6: 1136.3 | E6: 102.01 | F6: =E6*D6 -> 115913.96 | G6: 22609.55 | H6: 4141.6 | I6: =G6-H6 -> 18467.95 | J6: =G6+F6-H6 -> 134381.91 | K6: 134623.41 | L6: 56412.57 | M6: 14 | N6: =M6*K6 -> 1884727.7 | O6: 2708.7
B7: 4 | C7: S A I L | D7: 186.1 | E7: 413.05 | F7: =E7*D7 -> 76868.605 | G7: 31927.71 | H7: 732.51 | I7: =G7-H7 -> 31195.2 | J7: =G7+F7-H7 -> 108063.81 | K7: 108064.28 | L7: 111134.75 | M7: 7.35 | N7: =M7*K7 -> 794272.46 | O7: 4272.27
B8: 5 | C8: Jindal Stain. | D8: 738.75 | E8: 82.44 | F8: =E8*D8 -> 60902.55 | G8: 7460.33 | H8: 2934.03 | I8: =G8-H8 -> 4526.3 | J8: =G8+F8-H8 -> 65428.85 | K8: 65409.64 | L8: 44026.06 | M8: 10.82 | N8: =M8*K8 -> 707732.3 | O8: 3238.57
